Workbook

Sheet Dashboard
A1: HOUSE FLIP REHAB DASHBOARD
A2: WORKED EXAMPLE: $112,000 purchase | $285,000 ARV | 1,500 sf. Replace example inputs before evaluating a real property.
A3: Use Cost Dashboard to compare ballpark vs detailed costs. Positive variance means the detailed takeoff is above the original benchmark.
A4: ="Selected Rehab"&CHAR(10)&TEXT(SUM('Scope Builder'!U2:U251),"$#,##0") -> Selected Rehab $96,690 | D4: ="Critical / P0 Cost"&CHAR(10)&TEXT(SUMIFS('Scope Builder'!U2:U251,'Scope Builder'!A2:A251,"Yes",'Scope Builder'!I2:I251,"Critical")+SUMIFS('Scope Builder'!U2:U251,'Scope Builder'!A2:A251,"Yes",'Scope Builder'!K2:K251,"P0 - Immediate/Safety"),"$#,##0") -> Critical / P0 Cost $23,815 | G4: ="Projected Profit"&CHAR(10)&TEXT('Flip Analysis'!C12,"$#,##0") -> Projected Profit $38,270 | J4: ="Detailed MAO"&CHAR(10)&TEXT('Flip Analysis'!C16,"$#,##0") -> Detailed MAO $115,206
A8: RISK & SCOPE SUMMARY | H8: BUDGET BY PRIORITY
A9: Included Scope Items | D9: =COUNTIF('Scope Builder'!A2:A251,"Yes") -> 14 | H9: Priority | I9: Budget
A10: Critical Items | D10: =COUNTIFS('Scope Builder'!A2:A251,"Yes",'Scope Builder'!I2:I251,"Critical") -> 4 | H10: P0 - Immediate/Safety | I10: =SUMIFS('Scope Builder'!$U$2:$U$251,'Scope Builder'!$A$2:$A$251,"Yes",'Scope Builder'!$K$2:$K$251,H10) -> 0
A11: P0 Immediate/Safety | D11: =COUNTIFS('Scope Builder'!A2:A251,"Yes",'Scope Builder'!K2:K251,"P0 - Immediate/Safety") -> 0 | H11: P1 - Before Offer | I11: =SUMIFS('Scope Builder'!$U$2:$U$251,'Scope Builder'!$A$2:$A$251,"Yes",'Scope Builder'!$K$2:$K$251,H11) -> 24695
A12: P1 Before Offer | D12: =COUNTIFS('Scope Builder'!A2:A251,"Yes",'Scope Builder'!K2:K251,"P1 - Before Offer") -> 6 | H12: P2 - Before Sale | I12: =SUMIFS('Scope Builder'!$U$2:$U$251,'Scope Builder'!$A$2:$A$251,"Yes",'Scope Builder'!$K$2:$K$251,H12) -> 14630
A13: Permit-Required Items | D13: =COUNTIFS('Scope Builder'!A2:A251,"Yes",'Scope Builder'!W2:W251,"Yes") -> 4 | H13: P3 - Value Add | I13: =SUMIFS('Scope Builder'!$U$2:$U$251,'Scope Builder'!$A$2:$A$251,"Yes",'Scope Builder'!$K$2:$K$251,H13) -> 57365
A14: Contractor Quotes Entered | D14: =COUNTIFS('Scope Builder'!A2:A251,"Yes",'Scope Builder'!Q2:Q251,">0") -> 3 | H14: P4 - Optional | I14: =SUMIFS('Scope Builder'!$U$2:$U$251,'Scope Builder'!$A$2:$A$251,"Yes",'Scope Builder'!$K$2:$K$251,H14) -> 0
A16: BUDGET BY CATEGORY | H16: DEAL CHECKS
A17: Category | B17: Budget | H17: ARV | K17: ='Flip Analysis'!C5 -> 285000
A18: Appliances & Curb Appeal | B18: =SUMIFS('Scope Builder'!$U$2:$U$251,'Scope Builder'!$A$2:$A$251,"Yes",'Scope Builder'!$C$2:$C$251,A18) -> 495 | H18: Total Rehab | K18: ='Flip Analysis'!C6 -> 96690
A19: Basement & Environmental | B19: =SUMIFS('Scope Builder'!$U$2:$U$251,'Scope Builder'!$A$2:$A$251,"Yes",'Scope Builder'!$C$2:$C$251,A19) -> 0 | H19: Total Project Cost | K19: ='Flip Analysis'!C11 -> 246730
A20: Bathrooms | B20: =SUMIFS('Scope Builder'!$U$2:$U$251,'Scope Builder'!$A$2:$A$251,"Yes",'Scope Builder'!$C$2:$C$251,A20) -> 13970 | H20: Projected Profit | K20: ='Flip Analysis'!C12 -> 38270
A21: Electrical | B21: =SUMIFS('Scope Builder'!$U$2:$U$251,'Scope Builder'!$A$2:$A$251,"Yes",'Scope Builder'!$C$2:$C$251,A21) -> 3960 | H21: Profit Margin | K21: ='Flip Analysis'!C13 -> 0.1342807
A22: Exterior & Site | B22: =SUMIFS('Scope Builder'!$U$2:$U$251,'Scope Builder'!$A$2:$A$251,"Yes",'Scope Builder'!$C$2:$C$251,A22) -> 2530 | H22: Cash-on-Cost ROI | K22: ='Flip Analysis'!C14 -> 0.15510882
A23: Flooring | B23: =SUMIFS('Scope Builder'!$U$2:$U$251,'Scope Builder'!$A$2:$A$251,"Yes",'Scope Builder'!$C$2:$C$251,A23) -> 8360 | H23: 70% Rule MAO | K23: ='Flip Analysis'!C15 -> 102810
A24: HVAC | B24: =SUMIFS('Scope Builder'!$U$2:$U$251,'Scope Builder'!$A$2:$A$251,"Yes",'Scope Builder'!$C$2:$C$251,A24) -> 8690 | H24: Detailed MAO | K24: ='Flip Analysis'!C16 -> 115205.88
A25: Interior Finishes | B25: =SUMIFS('Scope Builder'!$U$2:$U$251,'Scope Builder'!$A$2:$A$251,"Yes",'Scope Builder'!$C$2:$C$251,A25) -> 5060 | H25: MAO Buffer | K25: ='Flip Analysis'!C17 -> 3205.8824
A26: Kitchen | B26: =SUMIFS('Scope Builder'!$U$2:$U$251,'Scope Builder'!$A$2:$A$251,"Yes",'Scope Builder'!$C$2:$C$251,A26) -> 26950
A27: Plumbing & Sewer | B27: =SUMIFS('Scope Builder'!$U$2:$U$251,'Scope Builder'!$A$2:$A$251,"Yes",'Scope Builder'!$C$2:$C$251,A27) -> 8250
A28: Roof & Attic | B28: =SUMIFS('Scope Builder'!$U$2:$U$251,'Scope Builder'!$A$2:$A$251,"Yes",'Scope Builder'!$C$2:$C$251,A28) -> 10890
A29: Soft Costs & Due Diligence | B29: =SUMIFS('Scope Builder'!$U$2:$U$251,'Scope Builder'!$A$2:$A$251,"Yes",'Scope Builder'!$C$2:$C$251,A29) -> 880
A30: Structure & Foundation | B30: =SUMIFS('Scope Builder'!$U$2:$U$251,'Scope Builder'!$A$2:$A$251,"Yes",'Scope Builder'!$C$2:$C$251,A30) -> 715
A31: Windows, Doors & Garage | B31: =SUMIFS('Scope Builder'!$U$2:$U$251,'Scope Builder'!$A$2:$A$251,"Yes",'Scope Builder'!$C$2:$C$251,A31) -> 5940
A44: PERFORMANCE KPIs
A45: ="MAO Buffer"&CHAR(10)&TEXT('Flip Analysis'!C17,"$#,##0;[Red]($#,##0);-") -> MAO Buffer $3,206 | D45: ="Rehab $ / sf"&CHAR(10)&TEXT('Flip Analysis'!C27,"$0.00")&"/sf" -> Rehab $ / sf $64.46/sf | G45: ="Contingency Remaining"&CHAR(10)&TEXT('Flip Analysis'!C30,"$#,##0;[Red]($#,##0);-") -> Contingency Remaining - | J45: ="Schedule Variance"&CHAR(10)&TEXT('Flip Analysis'!C24,"+0;-0;0")&" days" -> Schedule Variance +12 days
A49: ="Holding Cost / Day"&CHAR(10)&TEXT('Flip Analysis'!C26,"$#,##0.00;[Red]($#,##0.00);-") -> Holding Cost / Day $55.85 | D49: ="Profit / Day"&CHAR(10)&TEXT('Flip Analysis'!C40,"$#,##0;[Red]($#,##0);-") -> Profit / Day $336 | G49: ="ARV Variance"&CHAR(10)&TEXT('Flip Analysis'!C33,"$#,##0;[Red]($#,##0);-") -> ARV Variance $7,000 | J49: ="Actual-vs-Budget Variance"&CHAR(10)&TEXT('Flip Analysis'!C34,"$#,##0;[Red]($#,##0);-")&CHAR(10)&TEXT('Flip Analysis'!C35,"+0.0%;-0.0%;0.0%") -> Actual-vs-Budget Variance $3,110 +3.2%
A53: Actual-based KPIs use the blue Actual Performance Inputs on Project Inputs. Positive Schedule Variance and positive Actual-vs-Budget Variance indicate delay/overrun; positive MAO Buffer and ARV Variance are favorable.

Sheet Project Inputs
A1: HOUSE FLIP PROJECT INPUTS
A3: Property / Deal Assumptions | C3: Value | D3: Notes | F3: ACTUAL PERFORMANCE INPUTS
A4: Property Address | C4: EXAMPLE PROPERTY - St. Louis, MO 63116 | D4: WORKED EXAMPLE - replace with the subject property | F4: Planned Rehab Days | G4: 60 | H4: Example baseline; replace with plan
A5: City / ZIP | C5: St. Louis, MO 63116 | D5: Example market/ZIP | F5: Actual Rehab Days | G5: 72 | H5: Enter when rehab is complete / current actual
A6: Living Area (sf) | C6: 1500 | D6: Example living area | F6: Total Project Days | G6: 128 | H6: Acquisition through sale/close
A7: Beds / Baths | C7: 3 / 2 | D7: Example configuration | F7: Actual Rehab Cost | G7: 99800 | H7: Actual paid/committed rehab cost
A8: Purchase Price | C8: 112000 | D8: Illustrative acquisition price | F8: Actual Sale Price | G8: 292000 | H8: Enter final sale price when known
A9: After Repair Value (ARV) | C9: 285000 | D9: Illustrative comp-supported ARV
A10: Buying Closing Costs % | C10: 0.02 | D10: Example buying closing cost assumption
A11: Selling Costs % | C11: 0.08 | D11: Example selling cost assumption
A12: Holding Period (months) | C12: 5 | D12: Example acquisition-to-sale duration
A13: Monthly Holding Cost | C13: 1700 | D13: Interest + tax + insurance + utilities + lawn/security
A14: Financing / Points / Loan Fees | C14: 4500 | D14: Illustrative financing/points
A15: Default Rehab Contingency % | C15: 0.1 | D15: Example rehab contingency
A16: Target Profit | C16: 35000 | D16: Example minimum profit goal
A17: 70% Rule Benchmark | C17: 0.7 | D17: Quick-screening rule only
A19: WORKED EXAMPLE ACTIVE - replace blue/input cells for a real property.
A20: HOW TO USE
A21: 1 | B21: Enter or replace deal assumptions above.
A22: 2 | B22: Use Scope Builder: choose a Cost Code, paste the inspector/appraiser/designer note, enter quantity, priority and source.
A23: 3 | B23: Select cost basis: Low / Typical / High / Contractor Quote. Replace allowances with actual bids before purchase.
A24: 4 | B24: Dashboard and Flip Analysis update automatically for rows marked Include? = Yes.
A25: 5 | B25: Treat structural, active water, electrical safety, sewer, roof leaks and environmental issues as deal-risk items until professionally evaluated.

Sheet Scope Builder
A1: Include? | B1: Cost Code | C1: Category | D1: Trade | E1: Location / Room | F1: Inspector / Appraiser / Designer Note | G1: Work Type | H1: Source | I1: Severity | J1: Safety / Code? | K1: Priority | L1: Qty | M1: Unit | N1: Low | O1: Typical | P1: High | Q1: Contractor Quote (Total) | R1: Cost Basis | S1: Base Cost | T1: Contingency % | U1: Budgeted Cost | V1: Status | W1: Permit? | X1: Est. Days | Y1: ARV Impact | Z1: Value-Add Score (1-5) | AA1: Contractor | AB1: Dependency / Sequence | AC1: Notes | AD1: Material Qty | AE1: Material Unit Cost | AF1: Material Input Total | AG1: Labor Qty / Hours | AH1: Labor Unit Rate | AI1: Labor Input Total | AJ1: Equipment / Disposal | AK1: Permit / Other | AL1: Detailed Base Cost | AM1: Material Cost (Allocated) | AN1: Labor Cost (Allocated) | AO1: Other Cost (Allocated) | AP1: Contingency $ | AQ1: Material % | AR1: Labor % | AS1: Other % | AT1: Split Quality | AU1: Ballpark Basis | AV1: Ballpark Base Cost | AW1: Ballpark Budget incl. Contingency | AX1: Detailed Budget | AY1: Comparable Ballpark | AZ1: Variance $ | BA1: Variance % | BB1: Estimate Stage
A2: Yes | B2: SOFT-001 | C2: =IFERROR(VLOOKUP($B2,'Cost Library'!$A$2:$M$159,2,FALSE),"") -> Soft Costs & Due Diligence | D2: =IFERROR(VLOOKUP($B2,'Cost Library'!$A$2:$M$159,3,FALSE),"") -> Inspector | E2: Whole house | F2: General home inspection before contingency deadline | G2: =IFERROR(VLOOKUP($B2,'Cost Library'!$A$2:$M$159,5,FALSE),"") -> Inspection | H2: Home Inspector | I2: Medium | J2: No | K2: P1 - Before Offer | L2: 1 | M2: =IFERROR(VLOOKUP($B2,'Cost Library'!$A$2:$M$159,6,FALSE),"") -> project | N2: =IFERROR(VLOOKUP($B2,'Cost Library'!$A$2:$M$159,7,FALSE),0) -> 350 | O2: =IFERROR(VLOOKUP($B2,'Cost Library'!$A$2:$M$159,8,FALSE),0) -> 500 | P2: =IFERROR(VLOOKUP($B2,'Cost Library'!$A$2:$M$159,9,FALSE),0) -> 800 | Q2: 475 | R2: Contractor Quote | S2: =IF($A2<>"Yes",0,IF($R2="Detailed Breakdown",$AL2,IF($R2="Contractor Quote",$Q2,IF($R2="Low",$L2*$N2,IF($R2="High",$L2*$P2,$L2*$O2))))) -> 475 | T2: ='Project Inputs'!$C$15 -> 0.1 | U2: =IF($A2<>"Yes",0,$S2*(1+$T2)) -> 522.5 | V2: Complete | W2: =IFERROR(VLOOKUP($B2,'Cost Library'!$A$2:$M$159,10,FALSE),"") -> No | X2: 1 | Y2: 0 | Z2: 1 | AA2: Example Inspector | AB2: First due-diligence step | AC2: Illustrative quote | AF2: =IF(OR(AD2="",AE2=""),0,AD2*AE2) -> 0 | AI2: =IF(OR(AG2="",AH2=""),0,AG2*AH2) -> 0 | AL2: =SUM(AF2,AI2,AJ2,AK2) -> 0 | AM2: =IF($A2<>"Yes",0,IF($R2="Detailed Breakdown",$AF2,$S2*IFERROR(VLOOKUP($B2,'Cost Library'!$A$2:$Q$159,14,FALSE),0.4))) -> 0 | AN2: =IF($A2<>"Yes",0,IF($R2="Detailed Breakdown",$AI2,$S2*IFERROR(VLOOKUP($B2,'Cost Library'!$A$2:$Q$159,15,FALSE),0.5))) -> 0 | AO2: =IF($A2<>"Yes",0,IF($R2="Detailed Breakdown",$AJ2+$AK2,$S2*IFERROR(VLOOKUP($B2,'Cost Library'!$A$2:$Q$159,16,FALSE),0.1))) -> 475 | AP2: =IF($A2<>"Yes",0,$U2-$S2) -> 47.5 | AQ2: =IF($S2=0,0,$AM2/$S2) -> 0 | AR2: =IF($S2=0,0,$AN2/$S2) -> 0 | AS2: =IF($S2=0,0,$AO2/$S2) -> 1 | AT2: =IF($A2<>"Yes","",IF($R2="Detailed Breakdown","Detailed input",IF($R2="Contractor Quote","Estimated allocation - request vendor split","Planning allocation"))) -> Estimated allocation - request vendor split | AU2: Typical | AV2: =IF($A2<>"Yes",0,IF($AU2="Low",$L2*$N2,IF($AU2="High",$L2*$P2,$L2*$O2))) -> 500 | AW2: =IF($A2<>"Yes",0,$AV2*(1+$T2)) -> 550 | AX2: =IF(AND($A2="Yes",$AL2>0),$AL2*(1+$T2),0) -> 0 | AY2: =IF($AX2>0,$AW2,0) -> 0 | AZ2: =IF($AX2>0,$AX2-$AY2,0) -> 0 | BA2: =IF($AY2=0,0,$AZ2/$AY2) -> 0 | BB2: =IF($A2<>"Yes","",IF($Q2>0,"Quoted",IF($AL2>0,"Detailed","Ballpark"))) -> Quoted
A3: Yes | B3: SOFT-002 | C3: =IFERROR(VLOOKUP($B3,'Cost Library'!$A$2:$M$159,2,FALSE),"") -> Soft Costs & Due Diligence | D3: =IFERROR(VLOOKUP($B3,'Cost Library'!$A$2:$M$159,3,FALSE),"") -> Inspector | E3: Sewer lateral | F3: Camera scope of older sewer lateral | G3: =IFERROR(VLOOKUP($B3,'Cost Library'!$A$2:$M$159,5,FALSE),"") -> Inspection | H3: Home Inspector | I3: High | J3: No | K3: P1 - Before Offer | L3: 1 | M3: =IFERROR(VLOOKUP($B3,'Cost Library'!$A$2:$M$159,6,FALSE),"") -> project | N3: =IFERROR(VLOOKUP($B3,'Cost Library'!$A$2:$M$159,7,FALSE),0) -> 200 | O3: =IFERROR(VLOOKUP($B3,'Cost Library'!$A$2:$M$159,8,FALSE),0) -> 350 | P3: =IFERROR(VLOOKUP($B3,'Cost Library'!$A$2:$M$159,9,FALSE),0) -> 600 | Q3: 325 | R3: Contractor Quote | S3: =IF($A3<>"Yes",0,IF($R3="Detailed Breakdown",$AL3,IF($R3="Contractor Quote",$Q3,IF($R3="Low",$L3*$N3,IF($R3="High",$L3*$P3,$L3*$O3))))) -> 325 | T3: ='Project Inputs'!$C$15 -> 0.1 | U3: =IF($A3<>"Yes",0,$S3*(1+$T3)) -> 357.5 | V3: Complete | W3: =IFERROR(VLOOKUP($B3,'Cost Library'!$A$2:$M$159,10,FALSE),"") -> No | X3: 1 | Y3: 0 | Z3: 1 | AA3: Example Sewer Scope | AB3: After general inspection | AC3: Illustrative quote | AF3: =IF(OR(AD3="",AE3=""),0,AD3*AE3) -> 0 | AI3: =IF(OR(AG3="",AH3=""),0,AG3*AH3) -> 0 | AL3: =SUM(AF3,AI3,AJ3,AK3) -> 0 | AM3: =IF($A3<>"Yes",0,IF($R3="Detailed Breakdown",$AF3,$S3*IFERROR(VLOOKUP($B3,'Cost Library'!$A$2:$Q$159,14,FALSE),0.4))) -> 0 | AN3: =IF($A3<>"Yes",0,IF($R3="Detailed Breakdown",$AI3,$S3*IFERROR(VLOOKUP($B3,'Cost Library'!$A$2:$Q$159,15,FALSE),0.5))) -> 0 | AO3: =IF($A3<>"Yes",0,IF($R3="Detailed Breakdown",$AJ3+$AK3,$S3*IFERROR(VLOOKUP($B3,'Cost Library'!$A$2:$Q$159,16,FALSE),0.1))) -> 325 | AP3: =IF($A3<>"Yes",0,$U3-$S3) -> 32.5 | AQ3: =IF($S3=0,0,$AM3/$S3) -> 0 | AR3: =IF($S3=0,0,$AN3/$S3) -> 0 | AS3: =IF($S3=0,0,$AO3/$S3) -> 1 | AT3: =IF($A3<>"Yes","",IF($R3="Detailed Breakdown","Detailed input",IF($R3="Contractor Quote","Estimated allocation - request vendor split","Planning allocation"))) -> Estimated allocation - request vendor split | AU3: Typical | AV3: =IF($A3<>"Yes",0,IF($AU3="Low",$L3*$N3,IF($AU3="High",$L3*$P3,$L3*$O3))) -> 350 | AW3: =IF($A3<>"Yes",0,$AV3*(1+$T3)) -> 385 | AX3: =IF(AND($A3="Yes",$AL3>0),$AL3*(1+$T3),0) -> 0 | AY3: =IF($AX3>0,$AW3,0) -> 0 | AZ3: =IF($AX3>0,$AX3-$AY3,0) -> 0 | BA3: =IF($AY3=0,0,$AZ3/$AY3) -> 0 | BB3: =IF($A3<>"Yes","",IF($Q3>0,"Quoted",IF($AL3>0,"Detailed","Ballpark"))) -> Quoted
A4: Yes | B4: STR-001 | C4: =IFERROR(VLOOKUP($B4,'Cost Library'!$A$2:$M$159,2,FALSE),"") -> Structure & Foundation | D4: =IFERROR(VLOOKUP($B4,'Cost Library'!$A$2:$M$159,3,FALSE),"") -> Structural Engineer | E4: Basement | F4: Engineer review of stair-step cracking noted by inspector | G4: =IFERROR(VLOOKUP($B4,'Cost Library'!$A$2:$M$159,5,FALSE),"") -> Inspection | H4: Home Inspector | I4: Critical | J4: Yes | K4: P1 - Before Offer | L4: 1 | M4: =IFERROR(VLOOKUP($B4,'Cost Library'!$A$2:$M$159,6,FALSE),"") -> project | N4: =IFERROR(VLOOKUP($B4,'Cost Library'!$A$2:$M$159,7,FALSE),0) -> 400 | O4: =IFERROR(VLOOKUP($B4,'Cost Library'!$A$2:$M$159,8,FALSE),0) -> 750 | P4: =IFERROR(VLOOKUP($B4,'Cost Library'!$A$2:$M$159,9,FALSE),0) -> 1200 | Q4: 650 | R4: Contractor Quote | S4: =IF($A4<>"Yes",0,IF($R4="Detailed Breakdown",$AL4,IF($R4="Contractor Quote",$Q4,IF($R4="Low",$L4*$N4,IF($R4="High",$L4*$P4,$L4*$O4))))) -> 650 | T4: ='Project Inputs'!$C$15 -> 0.1 | U4: =IF($A4<>"Yes",0,$S4*(1+$T4)) -> 715 | V4: Complete | W4: =IFERROR(VLOOKUP($B4,'Cost Library'!$A$2:$M$159,10,FALSE),"") -> No | X4: 2 | Y4: 0 | Z4: 1 | AA4: Example Structural Engineer | AB4: Before committing to structural repairs | AC4: No stabilization assumed in example | AF4: =IF(OR(AD4="",AE4=""),0,AD4*AE4) -> 0 | AI4: =IF(OR(AG4="",AH4=""),0,AG4*AH4) -> 0 | AL4: =SUM(AF4,AI4,AJ4,AK4) -> 0 | AM4: =IF($A4<>"Yes",0,IF($R4="Detailed Breakdown",$AF4,$S4*IFERROR(VLOOKUP($B4,'Cost Library'!$A$2:$Q$159,14,FALSE),0.4))) -> 0 | AN4: =IF($A4<>"Yes",0,IF($R4="Detailed Breakdown",$AI4,$S4*IFERROR(VLOOKUP($B4,'Cost Library'!$A$2:$Q$159,15,FALSE),0.5))) -> 0 | AO4: =IF($A4<>"Yes",0,IF($R4="Detailed Breakdown",$AJ4+$AK4,$S4*IFERROR(VLOOKUP($B4,'Cost Library'!$A$2:$Q$159,16,FALSE),0.1))) -> 650 | AP4: =IF($A4<>"Yes",0,$U4-$S4) -> 65 | AQ4: =IF($S4=0,0,$AM4/$S4) -> 0 | AR4: =IF($S4=0,0,$AN4/$S4) -> 0 | AS4: =IF($S4=0,0,$AO4/$S4) -> 1 | AT4: =IF($A4<>"Yes","",IF($R4="Detailed Breakdown","Detailed input",IF($R4="Contractor Quote","Estimated allocation - request vendor split","Planning allocation"))) -> Estimated allocation - request vendor split | AU4: Typical | AV4: =IF($A4<>"Yes",0,IF($AU4="Low",$L4*$N4,IF($AU4="High",$L4*$P4,$L4*$O4))) -> 750 | AW4: =IF($A4<>"Yes",0,$AV4*(1+$T4)) -> 825 | AX4: =IF(AND($A4="Yes",$AL4>0),$AL4*(1+$T4),0) -> 0 | AY4: =IF($AX4>0,$AW4,0) -> 0 | AZ4: =IF($AX4>0,$AX4-$AY4,0) -> 0 | BA4: =IF($AY4=0,0,$AZ4/$AY4) -> 0 | BB4: =IF($A4<>"Yes","",IF($Q4>0,"Quoted",IF($AL4>0,"Detailed","Ballpark"))) -> Quoted
A5: Yes | B5: ROF-001 | C5: =IFERROR(VLOOKUP($B5,'Cost Library'!$A$2:$M$159,2,FALSE),"") -> Roof & Attic | D5: =IFERROR(VLOOKUP($B5,'Cost Library'!$A$2:$M$159,3,FALSE),"") -> Roofing | E5: Roof | F5: Replace aging asphalt-shingle roof; include tear-off and disposal | G5: =IFERROR(VLOOKUP($B5,'Cost Library'!$A$2:$M$159,5,FALSE),"") -> Replace | H5: Home Inspector | I5: Critical | J5: Yes | K5: P1 - Before Offer | L5: 1 | M5: =IFERROR(VLOOKUP($B5,'Cost Library'!$A$2:$M$159,6,FALSE),"") -> project | N5: =IFERROR(VLOOKUP($B5,'Cost Library'!$A$2:$M$159,7,FALSE),0) -> 5433 | O5: =IFERROR(VLOOKUP($B5,'Cost Library'!$A$2:$M$159,8,FALSE),0) -> 8155 | P5: =IFERROR(VLOOKUP($B5,'Cost Library'!$A$2:$M$159,9,FALSE),0) -> 11032 | R5: Detailed Breakdown | S5: =IF($A5<>"Yes",0,IF($R5="Detailed Breakdown",$AL5,IF($R5="Contractor Quote",$Q5,IF($R5="Low",$L5*$N5,IF($R5="High",$L5*$P5,$L5*$O5))))) -> 9900 | T5: ='Project Inputs'!$C$15 -> 0.1 | U5: =IF($A5<>"Yes",0,$S5*(1+$T5)) -> 10890 | V5: Quoted | W5: =IFERROR(VLOOKUP($B5,'Cost Library'!$A$2:$M$159,10,FALSE),"") -> Yes | X5: 4 | Y5: 12000 | Z5: 3 | AA5: Example Roofer | AB5: Complete before interior moisture repairs | AC5: Detailed example is above ballpark | AD5: 1 | AE5: 4200 | AF5: =IF(OR(AD5="",AE5=""),0,AD5*AE5) -> 4200 | AG5: 1 | AH5: 4000 | AI5: =IF(OR(AG5="",AH5=""),0,AG5*AH5) -> 4000 | AJ5: 1400 | AK5: 300 | AL5: =SUM(AF5,AI5,AJ5,AK5) -> 9900 | AM5: =IF($A5<>"Yes",0,IF($R5="Detailed Breakdown",$AF5,$S5*IFERROR(VLOOKUP($B5,'Cost Library'!$A$2:$Q$159,14,FALSE),0.4))) -> 4200 | AN5: =IF($A5<>"Yes",0,IF($R5="Detailed Breakdown",$AI5,$S5*IFERROR(VLOOKUP($B5,'Cost Library'!$A$2:$Q$159,15,FALSE),0.5))) -> 4000 | AO5: =IF($A5<>"Yes",0,IF($R5="Detailed Breakdown",$AJ5+$AK5,$S5*IFERROR(VLOOKUP($B5,'Cost Library'!$A$2:$Q$159,16,FALSE),0.1))) -> 1700 | AP5: =IF($A5<>"Yes",0,$U5-$S5) -> 990 | AQ5: =IF($S5=0,0,$AM5/$S5) -> 0.42424242 | AR5: =IF($S5=0,0,$AN5/$S5) -> 0.4040404 | AS5: =IF($S5=0,0,$AO5/$S5) -> 0.17171717 | AT5: =IF($A5<>"Yes","",IF($R5="Detailed Breakdown","Detailed input",IF($R5="Contractor Quote","Estimated allocation - request vendor split","Planning allocation"))) -> Detailed input | AU5: Typical | AV5: =IF($A5<>"Yes",0,IF($AU5="Low",$L5*$N5,IF($AU5="High",$L5*$P5,$L5*$O5))) -> 8155 | AW5: =IF($A5<>"Yes",0,$AV5*(1+$T5)) -> 8970.5 | AX5: =IF(AND($A5="Yes",$AL5>0),$AL5*(1+$T5),0) -> 10890 | AY5: =IF($AX5>0,$AW5,0) -> 8970.5 | AZ5: =IF($AX5>0,$AX5-$AY5,0) -> 1919.5 | BA5: =IF($AY5=0,0,$AZ5/$AY5) -> 0.21397915 | BB5: =IF($A5<>"Yes","",IF($Q5>0,"Quoted",IF($AL5>0,"Detailed","Ballpark"))) -> Detailed
A6: Yes | B6: ELE-001 | C6: =IFERROR(VLOOKUP($B6,'Cost Library'!$A$2:$M$159,2,FALSE),"") -> Electrical | D6: =IFERROR(VLOOKUP($B6,'Cost Library'!$A$2:$M$159,3,FALSE),"") -> Electrician | E6: Basement / service | F6: Replace obsolete electrical panel and correct grounding/labeling | G6: =IFERROR(VLOOKUP($B6,'Cost Library'!$A$2:$M$159,5,FALSE),"") -> Replace | H6: Home Inspector | I6: Critical | J6: Yes | K6: P1 - Before Offer | L6: 1 | M6: =IFERROR(VLOOKUP($B6,'Cost Library'!$A$2:$M$159,6,FALSE),"") -> project | N6: =IFERROR(VLOOKUP($B6,'Cost Library'!$A$2:$M$159,7,FALSE),0) -> 1800 | O6: =IFERROR(VLOOKUP($B6,'Cost Library'!$A$2:$M$159,8,FALSE),0) -> 3000 | P6: =IFERROR(VLOOKUP($B6,'Cost Library'!$A$2:$M$159,9,FALSE),0) -> 5000 | R6: Detailed Breakdown | S6: =IF($A6<>"Yes",0,IF($R6="Detailed Breakdown",$AL6,IF($R6="Contractor Quote",$Q6,IF($R6="Low",$L6*$N6,IF($R6="High",$L6*$P6,$L6*$O6))))) -> 3600 | T6: ='Project Inputs'!$C$15 -> 0.1 | U6: =IF($A6<>"Yes",0,$S6*(1+$T6)) -> 3960 | V6: Quoted | W6: =IFERROR(VLOOKUP($B6,'Cost Library'!$A$2:$M$159,10,FALSE),"") -> Yes | X6: 2 | Y6: 5000 | Z6: 2 | AA6: Example Electrician | AB6: Before finish work | AC6: Permit allowance included | AD6: 1 | AE6: 1450 | AF6: =IF(OR(AD6="",AE6=""),0,AD6*AE6) -> 1450 | AG6: 1 | AH6: 1800 | AI6: =IF(OR(AG6="",AH6=""),0,AG6*AH6) -> 1800 | AJ6: 0 | AK6: 350 | AL6: =SUM(AF6,AI6,AJ6,AK6) -> 3600 | AM6: =IF($A6<>"Yes",0,IF($R6="Detailed Breakdown",$AF6,$S6*IFERROR(VLOOKUP($B6,'Cost Library'!$A$2:$Q$159,14,FALSE),0.4))) -> 1450 | AN6: =IF($A6<>"Yes",0,IF($R6="Detailed Breakdown",$AI6,$S6*IFERROR(VLOOKUP($B6,'Cost Library'!$A$2:$Q$159,15,FALSE),0.5))) -> 1800 | AO6: =IF($A6<>"Yes",0,IF($R6="Detailed Breakdown",$AJ6+$AK6,$S6*IFERROR(VLOOKUP($B6,'Cost Library'!$A$2:$Q$159,16,FALSE),0.1))) -> 350 | AP6: =IF($A6<>"Yes",0,$U6-$S6) -> 360 | AQ6: =IF($S6=0,0,$AM6/$S6) -> 0.40277778 | AR6: =IF($S6=0,0,$AN6/$S6) -> 0.5 | AS6: =IF($S6=0,0,$AO6/$S6) -> 0.097222222 | AT6: =IF($A6<>"Yes","",IF($R6="Detailed Breakdown","Detailed input",IF($R6="Contractor Quote","Estimated allocation - request vendor split","Planning allocation"))) -> Detailed input | AU6: Typical | AV6: =IF($A6<>"Yes",0,IF($AU6="Low",$L6*$N6,IF($AU6="High",$L6*$P6,$L6*$O6))) -> 3000 | AW6: =IF($A6<>"Yes",0,$AV6*(1+$T6)) -> 3300 | AX6: =IF(AND($A6="Yes",$AL6>0),$AL6*(1+$T6),0) -> 3960 | AY6: =IF($AX6>0,$AW6,0) -> 3300 | AZ6: =IF($AX6>0,$AX6-$AY6,0) -> 660 | BA6: =IF($AY6=0,0,$AZ6/$AY6) -> 0.2 | BB6: =IF($A6<>"Yes","",IF($Q6>0,"Quoted",IF($AL6>0,"Detailed","Ballpark"))) -> Detailed
A7: Yes | B7: PLB-009 | C7: =IFERROR(VLOOKUP($B7,'Cost Library'!$A$2:$M$159,2,FALSE),"") -> Plumbing & Sewer | D7: =IFERROR(VLOOKUP($B7,'Cost Library'!$A$2:$M$159,3,FALSE),"") -> Plumber | E7: Front yard / sewer | F7: Spot repair of sewer lateral after root intrusion found on scope | G7: =IFERROR(VLOOKUP($B7,'Cost Library'!$A$2:$M$159,5,FALSE),"") -> Repair | H7: Specialist | I7: Critical | J7: Yes | K7: P1 - Before Offer | L7: 1 | M7: =IFERROR(VLOOKUP($B7,'Cost Library'!$A$2:$M$159,6,FALSE),"") -> project | N7: =IFERROR(VLOOKUP($B7,'Cost Library'!$A$2:$M$159,7,FALSE),0) -> 1500 | O7: =IFERROR(VLOOKUP($B7,'Cost Library'!$A$2:$M$159,8,FALSE),0) -> 5000 | P7: =IFERROR(VLOOKUP($B7,'Cost Library'!$A$2:$M$159,9,FALSE),0) -> 12000 | R7: Detailed Breakdown | S7: =IF($A7<>"Yes",0,IF($R7="Detailed Breakdown",$AL7,IF($R7="Contractor Quote",$Q7,IF($R7="Low",$L7*$N7,IF($R7="High",$L7*$P7,$L7*$O7))))) -> 7500 | T7: ='Project Inputs'!$C$15 -> 0.1 | U7: =IF($A7<>"Yes",0,$S7*(1+$T7)) -> 8250 | V7: Quoted | W7: =IFERROR(VLOOKUP($B7,'Cost Library'!$A$2:$M$159,10,FALSE),"") -> Yes | X7: 3 | Y7: 0 | Z7: 1 | AA7: Example Plumber | AB7: After sewer camera | AC7: Excavation included; high uncertainty item | AD7: 1 | AE7: 1800 | AF7: =IF(OR(AD7="",AE7=""),0,AD7*AE7) -> 1800 | AG7: 1 | AH7: 3000 | AI7: =IF(OR(AG7="",AH7=""),0,AG7*AH7) -> 3000 | AJ7: 2200 | AK7: 500 | AL7: =SUM(AF7,AI7,AJ7,AK7) -> 7500 | AM7: =IF($A7<>"Yes",0,IF($R7="Detailed Breakdown",$AF7,$S7*IFERROR(VLOOKUP($B7,'Cost Library'!$A$2:$Q$159,14,FALSE),0.4))) -> 1800 | AN7: =IF($A7<>"Yes",0,IF($R7="Detailed Breakdown",$AI7,$S7*IFERROR(VLOOKUP($B7,'Cost Library'!$A$2:$Q$159,15,FALSE),0.5))) -> 3000 | AO7: =IF($A7<>"Yes",0,IF($R7="Detailed Breakdown",$AJ7+$AK7,$S7*IFERROR(VLOOKUP($B7,'Cost Library'!$A$2:$Q$159,16,FALSE),0.1))) -> 2700 | AP7: =IF($A7<>"Yes",0,$U7-$S7) -> 750 | AQ7: =IF($S7=0,0,$AM7/$S7) -> 0.24 | AR7: =IF($S7=0,0,$AN7/$S7) -> 0.4 | AS7: =IF($S7=0,0,$AO7/$S7) -> 0.36 | AT7: =IF($A7<>"Yes","",IF($R7="Detailed Breakdown","Detailed input",IF($R7="Contractor Quote","Estimated allocation - request vendor split","Planning allocation"))) -> Detailed input | AU7: Typical | AV7: =IF($A7<>"Yes",0,IF($AU7="Low",$L7*$N7,IF($AU7="High",$L7*$P7,$L7*$O7))) -> 5000 | AW7: =IF($A7<>"Yes",0,$AV7*(1+$T7)) -> 5500 | AX7: =IF(AND($A7="Yes",$AL7>0),$AL7*(1+$T7),0) -> 8250 | AY7: =IF($AX7>0,$AW7,0) -> 5500 | AZ7: =IF($AX7>0,$AX7-$AY7,0) -> 2750 | BA7: =IF($AY7=0,0,$AZ7/$AY7) -> 0.5 | BB7: =IF($A7<>"Yes","",IF($Q7>0,"Quoted",IF($AL7>0,"Detailed","Ballpark"))) -> Detailed
A8: Yes | B8: HVAC-001 | C8: =IFERROR(VLOOKUP($B8,'Cost Library'!$A$2:$M$159,2,FALSE),"") -> HVAC | D8: =IFERROR(VLOOKUP($B8,'Cost Library'!$A$2:$M$159,3,FALSE),"") -> HVAC | E8: Whole house | F8: Replace end-of-life furnace/AC system | G8: =IFERROR(VLOOKUP($B8,'Cost Library'!$A$2:$M$159,5,FALSE),"") -> Replace | H8: Home Inspector | I8: High | J8: No | K8: P2 - Before Sale | L8: 1 | M8: =IFERROR(VLOOKUP($B8,'Cost Library'!$A$2:$M$159,6,FALSE),"") -> project | N8: =IFERROR(VLOOKUP($B8,'Cost Library'!$A$2:$M$159,7,FALSE),0) -> 4755 | O8: =IFERROR(VLOOKUP($B8,'Cost Library'!$A$2:$M$159,8,FALSE),0) -> 7133 | P8: =IFERROR(VLOOKUP($B8,'Cost Library'!$A$2:$M$159,9,FALSE),0) -> 11888 | R8: Detailed Breakdown | S8: =IF($A8<>"Yes",0,IF($R8="Detailed Breakdown",$AL8,IF($R8="Contractor Quote",$Q8,IF($R8="Low",$L8*$N8,IF($R8="High",$L8*$P8,$L8*$O8))))) -> 7900 | T8: ='Project Inputs'!$C$15 -> 0.1 | U8: =IF($A8<>"Yes",0,$S8*(1+$T8)) -> 8690 | V8: Quoted | W8: =IFERROR(VLOOKUP($B8,'Cost Library'!$A$2:$M$159,10,FALSE),"") -> Yes | X8: 3 | Y8: 8000 | Z8: 3 | AA8: Example HVAC Contractor | AB8: Before final paint touch-up | AC8: Illustrative installed-system breakdown | AD8: 1 | AE8: 4600 | AF8: =IF(OR(AD8="",AE8=""),0,AD8*AE8) -> 4600 | AG8: 1 | AH8: 2800 | AI8: =IF(OR(AG8="",AH8=""),0,AG8*AH8) -> 2800 | AJ8: 300 | AK8: 200 | AL8: =SUM(AF8,AI8,AJ8,AK8) -> 7900 | AM8: =IF($A8<>"Yes",0,IF($R8="Detailed Breakdown",$AF8,$S8*IFERROR(VLOOKUP($B8,'Cost Library'!$A$2:$Q$159,14,FALSE),0.4))) -> 4600 | AN8: =IF($A8<>"Yes",0,IF($R8="Detailed Breakdown",$AI8,$S8*IFERROR(VLOOKUP($B8,'Cost Library'!$A$2:$Q$159,15,FALSE),0.5))) -> 2800 | AO8: =IF($A8<>"Yes",0,IF($R8="Detailed Breakdown",$AJ8+$AK8,$S8*IFERROR(VLOOKUP($B8,'Cost Library'!$A$2:$Q$159,16,FALSE),0.1))) -> 500 | AP8: =IF($A8<>"Yes",0,$U8-$S8) -> 790 | AQ8: =IF($S8=0,0,$AM8/$S8) -> 0.58227848 | AR8: =IF($S8=0,0,$AN8/$S8) -> 0.35443038 | AS8: =IF($S8=0,0,$AO8/$S8) -> 0.063291139 | AT8: =IF($A8<>"Yes","",IF($R8="Detailed Breakdown","Detailed input",IF($R8="Contractor Quote","Estimated allocation - request vendor split","Planning allocation"))) -> Detailed input | AU8: Typical | AV8: =IF($A8<>"Yes",0,IF($AU8="Low",$L8*$N8,IF($AU8="High",$L8*$P8,$L8*$O8))) -> 7133 | AW8: =IF($A8<>"Yes",0,$AV8*(1+$T8)) -> 7846.3 | AX8: =IF(AND($A8="Yes",$AL8>0),$AL8*(1+$T8),0) -> 8690 | AY8: =IF($AX8>0,$AW8,0) -> 7846.3 | AZ8: =IF($AX8>0,$AX8-$AY8,0) -> 843.7 | BA8: =IF($AY8=0,0,$AZ8/$AY8) -> 0.10752839 | BB8: =IF($A8<>"Yes","",IF($Q8>0,"Quoted",IF($AL8>0,"Detailed","Ballpark"))) -> Detailed
A9: Yes | B9: INT-004 | C9: =IFERROR(VLOOKUP($B9,'Cost Library'!$A$2:$M$159,2,FALSE),"") -> Interior Finishes | D9: =IFERROR(VLOOKUP($B9,'Cost Library'!$A$2:$M$159,3,FALSE),"") -> Painting | E9: Whole house | F9: Neutral interior repaint for resale | G9: =IFERROR(VLOOKUP($B9,'Cost Library'!$A$2:$M$159,5,FALSE),"") -> Renovation | H9: Interior Designer | I9: Low | J9: No | K9: P3 - Value Add | L9: 1500 | M9: =IFERROR(VLOOKUP($B9,'Cost Library'!$A$2:$M$159,6,FALSE),"") -> sf | N9: =IFERROR(VLOOKUP($B9,'Cost Library'!$A$2:$M$159,7,FALSE),0) -> 1.5 | O9: =IFERROR(VLOOKUP($B9,'Cost Library'!$A$2:$M$159,8,FALSE),0) -> 3 | P9: =IFERROR(VLOOKUP($B9,'Cost Library'!$A$2:$M$159,9,FALSE),0) -> 5 | R9: Detailed Breakdown | S9: =IF($A9<>"Yes",0,IF($R9="Detailed Breakdown",$AL9,IF($R9="Contractor Quote",$Q9,IF($R9="Low",$L9*$N9,IF($R9="High",$L9*$P9,$L9*$O9))))) -> 4600 | T9: ='Project Inputs'!$C$15 -> 0.1 | U9: =IF($A9<>"Yes",0,$S9*(1+$T9)) -> 5060 | V9: Approved | W9: =IFERROR(VLOOKUP($B9,'Cost Library'!$A$2:$M$159,10,FALSE),"") -> No | X9: 5 | Y9: 8000 | Z9: 4 | AA9: Example Painting Crew | AB9: After major electrical/plumbing work | AC9: 35 gal paint/supplies + labor example | AD9: 35 | AE9: 45 | AF9: =IF(OR(AD9="",AE9=""),0,AD9*AE9) -> 1575 | AG9: 45 | AH9: 60 | AI9: =IF(OR(AG9="",AH9=""),0,AG9*AH9) -> 2700 | AJ9: 200 | AK9: 125 | AL9: =SUM(AF9,AI9,AJ9,AK9) -> 4600 | AM9: =IF($A9<>"Yes",0,IF($R9="Detailed Breakdown",$AF9,$S9*IFERROR(VLOOKUP($B9,'Cost Library'!$A$2:$Q$159,14,FALSE),0.4))) -> 1575 | AN9: =IF($A9<>"Yes",0,IF($R9="Detailed Breakdown",$AI9,$S9*IFERROR(VLOOKUP($B9,'Cost Library'!$A$2:$Q$159,15,FALSE),0.5))) -> 2700 | AO9: =IF($A9<>"Yes",0,IF($R9="Detailed Breakdown",$AJ9+$AK9,$S9*IFERROR(VLOOKUP($B9,'Cost Library'!$A$2:$Q$159,16,FALSE),0.1))) -> 325 | AP9: =IF($A9<>"Yes",0,$U9-$S9) -> 460 | AQ9: =IF($S9=0,0,$AM9/$S9) -> 0.3423913 | AR9: =IF($S9=0,0,$AN9/$S9) -> 0.58695652 | AS9: =IF($S9=0,0,$AO9/$S9) -> 0.070652174 | AT9: =IF($A9<>"Yes","",IF($R9="Detailed Breakdown","Detailed input",IF($R9="Contractor Quote","Estimated allocation - request vendor split","Planning allocation"))) -> Detailed input | AU9: Typical | AV9: =IF($A9<>"Yes",0,IF($AU9="Low",$L9*$N9,IF($AU9="High",$L9*$P9,$L9*$O9))) -> 4500 | AW9: =IF($A9<>"Yes",0,$AV9*(1+$T9)) -> 4950 | AX9: =IF(AND($A9="Yes",$AL9>0),$AL9*(1+$T9),0) -> 5060 | AY9: =IF($AX9>0,$AW9,0) -> 4950 | AZ9: =IF($AX9>0,$AX9-$AY9,0) -> 110 | BA9: =IF($AY9=0,0,$AZ9/$AY9) -> 0.022222222 | BB9: =IF($A9<>"Yes","",IF($Q9>0,"Quoted",IF($AL9>0,"Detailed","Ballpark"))) -> Detailed
A10: Yes | B10: FLR-001 | C10: =IFERROR(VLOOKUP($B10,'Cost Library'!$A$2:$M$159,2,FALSE),"") -> Flooring | D10: =IFERROR(VLOOKUP($B10,'Cost Library'!$A$2:$M$159,3,FALSE),"") -> Flooring | E10: Living areas / bedrooms | F10: Install LVP; 1,200 sf coverage plus ~10% material waste | G10: =IFERROR(VLOOKUP($B10,'Cost Library'!$A$2:$M$159,5,FALSE),"") -> Renovation | H10: Interior Designer | I10: Low | J10: No | K10: P3 - Value Add | L10: 1200 | M10: =IFERROR(VLOOKUP($B10,'Cost Library'!$A$2:$M$159,6,FALSE),"") -> sf | N10: =IFERROR(VLOOKUP($B10,'Cost Library'!$A$2:$M$159,7,FALSE),0) -> 3 | O10: =IFERROR(VLOOKUP($B10,'Cost Library'!$A$2:$M$159,8,FALSE),0) -> 6 | P10: =IFERROR(VLOOKUP($B10,'Cost Library'!$A$2:$M$159,9,FALSE),0) -> 10 | R10: Detailed Breakdown | S10: =IF($A10<>"Yes",0,IF($R10="Detailed Breakdown",$AL10,IF($R10="Contractor Quote",$Q10,IF($R10="Low",$L10*$N10,IF($R10="High",$L10*$P10,$L10*$O10))))) -> 7600 | T10: ='Project Inputs'!$C$15 -> 0.1 | U10: =IF($A10<>"Yes",0,$S10*(1+$T10)) -> 8360 | V10: Approved | W10: =IFERROR(VLOOKUP($B10,'Cost Library'!$A$2:$M$159,10,FALSE),"") -> No | X10: 4 | Y10: 10000 | Z10: 5 | AA10: Example Flooring Crew | AB10: After painting; before final trim | AC10: Detailed takeoff uses 1,320 sf material | AD10: 1320 | AE10: 2.95 | AF10: =IF(OR(AD10="",AE10=""),0,AD10*AE10) -> 3894 | AG10: 1200 | AH10: 2.4 | AI10: =IF(OR(AG10="",AH10=""),0,AG10*AH10) -> 2880 | AJ10: 600 | AK10: 226 | AL10: =SUM(AF10,AI10,AJ10,AK10) -> 7600 | AM10: =IF($A10<>"Yes",0,IF($R10="Detailed Breakdown",$AF10,$S10*IFERROR(VLOOKUP($B10,'Cost Library'!$A$2:$Q$159,14,FALSE),0.4))) -> 3894 | AN10: =IF($A10<>"Yes",0,IF($R10="Detailed Breakdown",$AI10,$S10*IFERROR(VLOOKUP($B10,'Cost Library'!$A$2:$Q$159,15,FALSE),0.5))) -> 2880 | AO10: =IF($A10<>"Yes",0,IF($R10="Detailed Breakdown",$AJ10+$AK10,$S10*IFERROR(VLOOKUP($B10,'Cost Library'!$A$2:$Q$159,16,FALSE),0.1))) -> 826 | AP10: =IF($A10<>"Yes",0,$U10-$S10) -> 760 | AQ10: =IF($S10=0,0,$AM10/$S10) -> 0.51236842 | AR10: =IF($S10=0,0,$AN10/$S10) -> 0.37894737 | AS10: =IF($S10=0,0,$AO10/$S10) -> 0.10868421 | AT10: =IF($A10<>"Yes","",IF($R10="Detailed Breakdown","Detailed input",IF($R10="Contractor Quote","Estimated allocation - request vendor split","Planning allocation"))) -> Detailed input | AU10: Typical | AV10: =IF($A10<>"Yes",0,IF($AU10="Low",$L10*$N10,IF($AU10="High",$L10*$P10,$L10*$O10))) -> 7200 | AW10: =IF($A10<>"Yes",0,$AV10*(1+$T10)) -> 7920 | AX10: =IF(AND($A10="Yes",$AL10>0),$AL10*(1+$T10),0) -> 8360 | AY10: =IF($AX10>0,$AW10,0) -> 7920 | AZ10: =IF($AX10>0,$AX10-$AY10,0) -> 440 | BA10: =IF($AY10=0,0,$AZ10/$AY10) -> 0.055555556 | BB10: =IF($A10<>"Yes","",IF($Q10>0,"Quoted",IF($AL10>0,"Detailed","Ballpark"))) -> Detailed
A11: Yes | B11: KIT-001 | C11: =IFERROR(VLOOKUP($B11,'Cost Library'!$A$2:$M$159,2,FALSE),"") -> Kitchen | D11: =IFERROR(VLOOKUP($B11,'Cost Library'!$A$2:$M$159,3,FALSE),"") -> General Contractor | E11: Kitchen | F11: Mid-range flip kitchen: cabinets, counters, appliances, lighting and finish work | G11: =IFERROR(VLOOKUP($B11,'Cost Library'!$A$2:$M$159,5,FALSE),"") -> Renovation | H11: Interior Designer | I11: Medium | J11: No | K11: P3 - Value Add | L11: 1 | M11: =IFERROR(VLOOKUP($B11,'Cost Library'!$A$2:$M$159,6,FALSE),"") -> project | N11: =IFERROR(VLOOKUP($B11,'Cost Library'!$A$2:$M$159,7,FALSE),0) -> 13800 | O11: =IFERROR(VLOOKUP($B11,'Cost Library'!$A$2:$M$159,8,FALSE),0) -> 26000 | P11: =IFERROR(VLOOKUP($B11,'Cost Library'!$A$2:$M$159,9,FALSE),0) -> 38600 | R11: Detailed Breakdown | S11: =IF($A11<>"Yes",0,IF($R11="Detailed Breakdown",$AL11,IF($R11="Contractor Quote",$Q11,IF($R11="Low",$L11*$N11,IF($R11="High",$L11*$P11,$L11*$O11))))) -> 24500 | T11: ='Project Inputs'!$C$15 -> 0.1 | U11: =IF($A11<>"Yes",0,$S11*(1+$T11)) -> 26950 | V11: Approved | W11: =IFERROR(VLOOKUP($B11,'Cost Library'!$A$2:$M$159,10,FALSE),"") -> Sometimes | X11: 14 | Y11: 25000 | Z11: 5 | AA11: Example GC / Kitchen Crew | AB11: Rough plumbing/electrical before cabinets | AC11: Illustrative bundled material and labor | AD11: 1 | AE11: 14000 | AF11: =IF(OR(AD11="",AE11=""),0,AD11*AE11) -> 14000 | AG11: 1 | AH11: 8000 | AI11: =IF(OR(AG11="",AH11=""),0,AG11*AH11) -> 8000 | AJ11: 1200 | AK11: 1300 | AL11: =SUM(AF11,AI11,AJ11,AK11) -> 24500 | AM11: =IF($A11<>"Yes",0,IF($R11="Detailed Breakdown",$AF11,$S11*IFERROR(VLOOKUP($B11,'Cost Library'!$A$2:$Q$159,14,FALSE),0.4))) -> 14000 | AN11: =IF($A11<>"Yes",0,IF($R11="Detailed Breakdown",$AI11,$S11*IFERROR(VLOOKUP($B11,'Cost Library'!$A$2:$Q$159,15,FALSE),0.5))) -> 8000 | AO11: =IF($A11<>"Yes",0,IF($R11="Detailed Breakdown",$AJ11+$AK11,$S11*IFERROR(VLOOKUP($B11,'Cost Library'!$A$2:$Q$159,16,FALSE),0.1))) -> 2500 | AP11: =IF($A11<>"Yes",0,$U11-$S11) -> 2450 | AQ11: =IF($S11=0,0,$AM11/$S11) -> 0.57142857 | AR11: =IF($S11=0,0,$AN11/$S11) -> 0.32653061 | AS11: =IF($S11=0,0,$AO11/$S11) -> 0.10204082 | AT11: =IF($A11<>"Yes","",IF($R11="Detailed Breakdown","Detailed input",IF($R11="Contractor Quote","Estimated allocation - request vendor split","Planning allocation"))) -> Detailed input | AU11: Typical | AV11: =IF($A11<>"Yes",0,IF($AU11="Low",$L11*$N11,IF($AU11="High",$L11*$P11,$L11*$O11))) -> 26000 | AW11: =IF($A11<>"Yes",0,$AV11*(1+$T11)) -> 28600 | AX11: =IF(AND($A11="Yes",$AL11>0),$AL11*(1+$T11),0) -> 26950 | AY11: =IF($AX11>0,$AW11,0) -> 28600 | AZ11: =IF($AX11>0,$AX11-$AY11,0) -> -1650 | BA11: =IF($AY11=0,0,$AZ11/$AY11) -> -0.057692308 | BB11: =IF($A11<>"Yes","",IF($Q11>0,"Quoted",IF($AL11>0,"Detailed","Ballpark"))) -> Detailed
A12: Yes | B12: BAT-001 | C12: =IFERROR(VLOOKUP($B12,'Cost Library'!$A$2:$M$159,2,FALSE),"") -> Bathrooms | D12: =IFERROR(VLOOKUP($B12,'Cost Library'!$A$2:$M$159,3,FALSE),"") -> General Contractor | E12: Main bathroom | F12: Full bath refresh with waterproofing, vanity, fixtures, tile and paint | G12: =IFERROR(VLOOKUP($B12,'Cost Library'!$A$2:$M$159,5,FALSE),"") -> Renovation | H12: Interior Designer | I12: Medium | J12: No | K12: P3 - Value Add | L12: 1 | M12: =IFERROR(VLOOKUP($B12,'Cost Library'!$A$2:$M$159,6,FALSE),"") -> bath | N12: =IFERROR(VLOOKUP($B12,'Cost Library'!$A$2:$M$159,7,FALSE),0) -> 6423 | O12: =IFERROR(VLOOKUP($B12,'Cost Library'!$A$2:$M$159,8,FALSE),0) -> 11246 | P12: =IFERROR(VLOOKUP($B12,'Cost Library'!$A$2:$M$159,9,FALSE),0) -> 16519 | R12: Detailed Breakdown | S12: =IF($A12<>"Yes",0,IF($R12="Detailed Breakdown",$AL12,IF($R12="Contractor Quote",$Q12,IF($R12="Low",$L12*$N12,IF($R12="High",$L12*$P12,$L12*$O12))))) -> 12700 | T12: ='Project Inputs'!$C$15 -> 0.1 | U12: =IF($A12<>"Yes",0,$S12*(1+$T12)) -> 13970 | V12: Approved | W12: =IFERROR(VLOOKUP($B12,'Cost Library'!$A$2:$M$159,10,FALSE),"") -> Sometimes | X12: 8 | Y12: 15000 | Z12: 5 | AA12: Example Bath Contractor | AB12: After rough plumbing/electrical | AC12: Detailed estimate slightly above ballpark | AD12: 1 | AE12: 6800 | AF12: =IF(OR(AD12="",AE12=""),0,AD12*AE12) -> 6800 | AG12: 1 | AH12: 4600 | AI12: =IF(OR(AG12="",AH12=""),0,AG12*AH12) -> 4600 | AJ12: 700 | AK12: 600 | AL12: =SUM(AF12,AI12,AJ12,AK12) -> 12700 | AM12: =IF($A12<>"Yes",0,IF($R12="Detailed Breakdown",$AF12,$S12*IFERROR(VLOOKUP($B12,'Cost Library'!$A$2:$Q$159,14,FALSE),0.4))) -> 6800 | AN12: =IF($A12<>"Yes",0,IF($R12="Detailed Breakdown",$AI12,$S12*IFERROR(VLOOKUP($B12,'Cost Library'!$A$2:$Q$159,15,FALSE),0.5))) -> 4600 | AO12: =IF($A12<>"Yes",0,IF($R12="Detailed Breakdown",$AJ12+$AK12,$S12*IFERROR(VLOOKUP($B12,'Cost Library'!$A$2:$Q$159,16,FALSE),0.1))) -> 1300 | AP12: =IF($A12<>"Yes",0,$U12-$S12) -> 1270 | AQ12: =IF($S12=0,0,$AM12/$S12) -> 0.53543307 | AR12: =IF($S12=0,0,$AN12/$S12) -> 0.36220472 | AS12: =IF($S12=0,0,$AO12/$S12) -> 0.1023622 | AT12: =IF($A12<>"Yes","",IF($R12="Detailed Breakdown","Detailed input",IF($R12="Contractor Quote","Estimated allocation - request vendor split","Planning allocation"))) -> Detailed input | AU12: Typical | AV12: =IF($A12<>"Yes",0,IF($AU12="Low",$L12*$N12,IF($AU12="High",$L12*$P12,$L12*$O12))) -> 11246 | AW12: =IF($A12<>"Yes",0,$AV12*(1+$T12)) -> 12370.6 | AX12: =IF(AND($A12="Yes",$AL12>0),$AL12*(1+$T12),0) -> 13970 | AY12: =IF($AX12>0,$AW12,0) -> 12370.6 | AZ12: =IF($AX12>0,$AX12-$AY12,0) -> 1599.4 | BA12: =IF($AY12=0,0,$AZ12/$AY12) -> 0.12929041 | BB12: =IF($A12<>"Yes","",IF($Q12>0,"Quoted",IF($AL12>0,"Detailed","Ballpark"))) -> Detailed
A13: Yes | B13: APP-005 | C13: =IFERROR(VLOOKUP($B13,'Cost Library'!$A$2:$M$159,2,FALSE),"") -> Appliances & Curb Appeal | D13: =IFERROR(VLOOKUP($B13,'Cost Library'!$A$2:$M$159,3,FALSE),"") -> Painting | E13: Front entry | F13: Refinish/paint front door for curb appeal | G13: =IFERROR(VLOOKUP($B13,'Cost Library'!$A$2:$M$159,5,FALSE),"") -> Renovation | H13: Interior Designer | I13: Low | J13: No | K13: P3 - Value Add | L13: 1 | M13: =IFERROR(VLOOKUP($B13,'Cost Library'!$A$2:$M$159,6,FALSE),"") -> each | N13: =IFERROR(VLOOKUP($B13,'Cost Library'!$A$2:$M$159,7,FALSE),0) -> 200 | O13: =IFERROR(VLOOKUP($B13,'Cost Library'!$A$2:$M$159,8,FALSE),0) -> 400 | P13: =IFERROR(VLOOKUP($B13,'Cost Library'!$A$2:$M$159,9,FALSE),0) -> 700 | R13: Detailed Breakdown | S13: =IF($A13<>"Yes",0,IF($R13="Detailed Breakdown",$AL13,IF($R13="Contractor Quote",$Q13,IF($R13="Low",$L13*$N13,IF($R13="High",$L13*$P13,$L13*$O13))))) -> 450 | T13: ='Project Inputs'!$C$15 -> 0.1 | U13: =IF($A13<>"Yes",0,$S13*(1+$T13)) -> 495 | V13: Approved | W13: =IFERROR(VLOOKUP($B13,'Cost Library'!$A$2:$M$159,10,FALSE),"") -> No | X13: 1 | Y13: 1500 | Z13: 3 | AA13: Example Handyman | AB13: Late-stage curb appeal | AC13: Small value-add item | AD13: 1 | AE13: 150 | AF13: =IF(OR(AD13="",AE13=""),0,AD13*AE13) -> 150 | AG13: 1 | AH13: 250 | AI13: =IF(OR(AG13="",AH13=""),0,AG13*AH13) -> 250 | AJ13: 0 | AK13: 50 | AL13: =SUM(AF13,AI13,AJ13,AK13) -> 450 | AM13: =IF($A13<>"Yes",0,IF($R13="Detailed Breakdown",$AF13,$S13*IFERROR(VLOOKUP($B13,'Cost Library'!$A$2:$Q$159,14,FALSE),0.4))) -> 150 | AN13: =IF($A13<>"Yes",0,IF($R13="Detailed Breakdown",$AI13,$S13*IFERROR(VLOOKUP($B13,'Cost Library'!$A$2:$Q$159,15,FALSE),0.5))) -> 250 | AO13: =IF($A13<>"Yes",0,IF($R13="Detailed Breakdown",$AJ13+$AK13,$S13*IFERROR(VLOOKUP($B13,'Cost Library'!$A$2:$Q$159,16,FALSE),0.1))) -> 50 | AP13: =IF($A13<>"Yes",0,$U13-$S13) -> 45 | AQ13: =IF($S13=0,0,$AM13/$S13) -> 0.33333333 | AR13: =IF($S13=0,0,$AN13/$S13) -> 0.55555556 | AS13: =IF($S13=0,0,$AO13/$S13) -> 0.11111111 | AT13: =IF($A13<>"Yes","",IF($R13="Detailed Breakdown","Detailed input",IF($R13="Contractor Quote","Estimated allocation - request vendor split","Planning allocation"))) -> Detailed input | AU13: Typical | AV13: =IF($A13<>"Yes",0,IF($AU13="Low",$L13*$N13,IF($AU13="High",$L13*$P13,$L13*$O13))) -> 400 | AW13: =IF($A13<>"Yes",0,$AV13*(1+$T13)) -> 440 | AX13: =IF(AND($A13="Yes",$AL13>0),$AL13*(1+$T13),0) -> 495 | AY13: =IF($AX13>0,$AW13,0) -> 440 | AZ13: =IF($AX13>0,$AX13-$AY13,0) -> 55 | BA13: =IF($AY13=0,0,$AZ13/$AY13) -> 0.125 | BB13: =IF($A13<>"Yes","",IF($Q13>0,"Quoted",IF($AL13>0,"Detailed","Ballpark"))) -> Detailed
A14: Yes | B14: WND-002 | C14: =IFERROR(VLOOKUP($B14,'Cost Library'!$A$2:$M$159,2,FALSE),"") -> Windows, Doors & Garage | D14: =IFERROR(VLOOKUP($B14,'Cost Library'!$A$2:$M$159,3,FALSE),"") -> Window | E14: Bedrooms / living room | F14: Replace six failed/dated standard windows | G14: =IFERROR(VLOOKUP($B14,'Cost Library'!$A$2:$M$159,5,FALSE),"") -> Replace | H14: Home Inspector | I14: Medium | J14: No | K14: P2 - Before Sale | L14: 6 | M14: =IFERROR(VLOOKUP($B14,'Cost Library'!$A$2:$M$159,6,FALSE),"") -> each | N14: =IFERROR(VLOOKUP($B14,'Cost Library'!$A$2:$M$159,7,FALSE),0) -> 400 | O14: =IFERROR(VLOOKUP($B14,'Cost Library'!$A$2:$M$159,8,FALSE),0) -> 750 | P14: =IFERROR(VLOOKUP($B14,'Cost Library'!$A$2:$M$159,9,FALSE),0) -> 1200 | R14: Detailed Breakdown | S14: =IF($A14<>"Yes",0,IF($R14="Detailed Breakdown",$AL14,IF($R14="Contractor Quote",$Q14,IF($R14="Low",$L14*$N14,IF($R14="High",$L14*$P14,$L14*$O14))))) -> 5400 | T14: ='Project Inputs'!$C$15 -> 0.1 | U14: =IF($A14<>"Yes",0,$S14*(1+$T14)) -> 5940 | V14: Quoted | W14: =IFERROR(VLOOKUP($B14,'Cost Library'!$A$2:$M$159,10,FALSE),"") -> Sometimes | X14: 3 | Y14: 6000 | Z14: 3 | AA14: Example Window Installer | AB14: Before interior trim touch-up | AC14: Six-window example | AD14: 6 | AE14: 550 | AF14: =IF(OR(AD14="",AE14=""),0,AD14*AE14) -> 3300 | AG14: 6 | AH14: 300 | AI14: =IF(OR(AG14="",AH14=""),0,AG14*AH14) -> 1800 | AJ14: 200 | AK14: 100 | AL14: =SUM(AF14,AI14,AJ14,AK14) -> 5400 | AM14: =IF($A14<>"Yes",0,IF($R14="Detailed Breakdown",$AF14,$S14*IFERROR(VLOOKUP($B14,'Cost Library'!$A$2:$Q$159,14,FALSE),0.4))) -> 3300 | AN14: =IF($A14<>"Yes",0,IF($R14="Detailed Breakdown",$AI14,$S14*IFERROR(VLOOKUP($B14,'Cost Library'!$A$2:$Q$159,15,FALSE),0.5))) -> 1800 | AO14: =IF($A14<>"Yes",0,IF($R14="Detailed Breakdown",$AJ14+$AK14,$S14*IFERROR(VLOOKUP($B14,'Cost Library'!$A$2:$Q$159,16,FALSE),0.1))) -> 300 | AP14: =IF($A14<>"Yes",0,$U14-$S14) -> 540 | AQ14: =IF($S14=0,0,$AM14/$S14) -> 0.61111111 | AR14: =IF($S14=0,0,$AN14/$S14) -> 0.33333333 | AS14: =IF($S14=0,0,$AO14/$S14) -> 0.055555556 | AT14: =IF($A14<>"Yes","",IF($R14="Detailed Breakdown","Detailed input",IF($R14="Contractor Quote","Estimated allocation - request vendor split","Planning allocation"))) -> Detailed input | AU14: Typical | AV14: =IF($A14<>"Yes",0,IF($AU14="Low",$L14*$N14,IF($AU14="High",$L14*$P14,$L14*$O14))) -> 4500 | AW14: =IF($A14<>"Yes",0,$AV14*(1+$T14)) -> 4950 | AX14: =IF(AND($A14="Yes",$AL14>0),$AL14*(1+$T14),0) -> 5940 | AY14: =IF($AX14>0,$AW14,0) -> 4950 | AZ14: =IF($AX14>0,$AX14-$AY14,0) -> 990 | BA14: =IF($AY14=0,0,$AZ14/$AY14) -> 0.2 | BB14: =IF($A14<>"Yes","",IF($Q14>0,"Quoted",IF($AL14>0,"Detailed","Ballpark"))) -> Detailed
A15: Yes | B15: EXT-013 | C15: =IFERROR(VLOOKUP($B15,'Cost Library'!$A$2:$M$159,2,FALSE),"") -> Exterior & Site | D15: =IFERROR(VLOOKUP($B15,'Cost Library'!$A$2:$M$159,3,FALSE),"") -> Landscaping | E15: Front / rear yard | F15: Basic landscaping and curb-appeal refresh | G15: =IFERROR(VLOOKUP($B15,'Cost Library'!$A$2:$M$159,5,FALSE),"") -> Renovation | H15: Interior Designer | I15: Low | J15: No | K15: P3 - Value Add | L15: 1 | M15: =IFERROR(VLOOKUP($B15,'Cost Library'!$A$2:$M$159,6,FALSE),"") -> project | N15: =IFERROR(VLOOKUP($B15,'Cost Library'!$A$2:$M$159,7,FALSE),0) -> 500 | O15: =IFERROR(VLOOKUP($B15,'Cost Library'!$A$2:$M$159,8,FALSE),0) -> 2000 | P15: =IFERROR(VLOOKUP($B15,'Cost Library'!$A$2:$M$159,9,FALSE),0) -> 6000 | R15: Detailed Breakdown | S15: =IF($A15<>"Yes",0,IF($R15="Detailed Breakdown",$AL15,IF($R15="Contractor Quote",$Q15,IF($R15="Low",$L15*$N15,IF($R15="High",$L15*$P15,$L15*$O15))))) -> 2300 | T15: ='Project Inputs'!$C$15 -> 0.1 | U15: =IF($A15<>"Yes",0,$S15*(1+$T15)) -> 2530 | V15: Approved | W15: =IFERROR(VLOOKUP($B15,'Cost Library'!$A$2:$M$159,10,FALSE),"") -> No | X15: 2 | Y15: 3000 | Z15: 4 | AA15: Example Landscape Crew | AB15: Final exterior phase | AC15: Mulch, pruning, lawn repair and cleanup | AD15: 1 | AE15: 1000 | AF15: =IF(OR(AD15="",AE15=""),0,AD15*AE15) -> 1000 | AG15: 1 | AH15: 1000 | AI15: =IF(OR(AG15="",AH15=""),0,AG15*AH15) -> 1000 | AJ15: 300 | AK15: 0 | AL15: =SUM(AF15,AI15,AJ15,AK15) -> 2300 | AM15: =IF($A15<>"Yes",0,IF($R15="Detailed Breakdown",$AF15,$S15*IFERROR(VLOOKUP($B15,'Cost Library'!$A$2:$Q$159,14,FALSE),0.4))) -> 1000 | AN15: =IF($A15<>"Yes",0,IF($R15="Detailed Breakdown",$AI15,$S15*IFERROR(VLOOKUP($B15,'Cost Library'!$A$2:$Q$159,15,FALSE),0.5))) -> 1000 | AO15: =IF($A15<>"Yes",0,IF($R15="Detailed Breakdown",$AJ15+$AK15,$S15*IFERROR(VLOOKUP($B15,'Cost Library'!$A$2:$Q$159,16,FALSE),0.1))) -> 300 | AP15: =IF($A15<>"Yes",0,$U15-$S15) -> 230 | AQ15: =IF($S15=0,0,$AM15/$S15) -> 0.43478261 | AR15: =IF($S15=0,0,$AN15/$S15) -> 0.43478261 | AS15: =IF($S15=0,0,$AO15/$S15) -> 0.13043478 | AT15: =IF($A15<>"Yes","",IF($R15="Detailed Breakdown","Detailed input",IF($R15="Contractor Quote","Estimated allocation - request vendor split","Planning allocation"))) -> Detailed input | AU15: Typical | AV15: =IF($A15<>"Yes",0,IF($AU15="Low",$L15*$N15,IF($AU15="High",$L15*$P15,$L15*$O15))) -> 2000 | AW15: =IF($A15<>"Yes",0,$AV15*(1+$T15)) -> 2200 | AX15: =IF(AND($A15="Yes",$AL15>0),$AL15*(1+$T15),0) -> 2530 | AY15: =IF($AX15>0,$AW15,0) -> 2200 | AZ15: =IF($AX15>0,$AX15-$AY15,0) -> 330 | BA15: =IF($AY15=0,0,$AZ15/$AY15) -> 0.15 | BB15: =IF($A15<>"Yes","",IF($Q15>0,"Quoted",IF($AL15>0,"Detailed","Ballpark"))) -> Detailed
A16: No | C16: =IFERROR(VLOOKUP($B16,'Cost Library'!$A$2:$M$159,2,FALSE),"") | D16: =IFERROR(VLOOKUP($B16,'Cost Library'!$A$2:$M$159,3,FALSE),"") | G16: =IFERROR(VLOOKUP($B16,'Cost Library'!$A$2:$M$159,5,FALSE),"") | L16: 1 | M16: =IFERROR(VLOOKUP($B16,'Cost Library'!$A$2:$M$159,6,FALSE),"") | N16: =IFERROR(VLOOKUP($B16,'Cost Library'!$A$2:$M$159,7,FALSE),0) -> 0 | O16: =IFERROR(VLOOKUP($B16,'Cost Library'!$A$2:$M$159,8,FALSE),0) -> 0 | P16: =IFERROR(VLOOKUP($B16,'Cost Library'!$A$2:$M$159,9,FALSE),0) -> 0 | R16: Typical | S16: =IF($A16<>"Yes",0,IF($R16="Detailed Breakdown",$AL16,IF($R16="Contractor Quote",$Q16,IF($R16="Low",$L16*$N16,IF($R16="High",$L16*$P16,$L16*$O16))))) -> 0 | T16: ='Project Inputs'!$C$15 -> 0.1 | U16: =IF($A16<>"Yes",0,$S16*(1+$T16)) -> 0 | V16: Not Started | W16: =IFERROR(VLOOKUP($B16,'Cost Library'!$A$2:$M$159,10,FALSE),"") | AF16: =IF(OR(AD16="",AE16=""),0,AD16*AE16) -> 0 | AI16: =IF(OR(AG16="",AH16=""),0,AG16*AH16) -> 0 | AL16: =SUM(AF16,AI16,AJ16,AK16) -> 0 | AM16: =IF($A16<>"Yes",0,IF($R16="Detailed Breakdown",$AF16,$S16*IFERROR(VLOOKUP($B16,'Cost Library'!$A$2:$Q$159,14,FALSE),0.4))) -> 0 | AN16: =IF($A16<>"Yes",0,IF($R16="Detailed Breakdown",$AI16,$S16*IFERROR(VLOOKUP($B16,'Cost Library'!$A$2:$Q$159,15,FALSE),0.5))) -> 0 | AO16: =IF($A16<>"Yes",0,IF($R16="Detailed Breakdown",$AJ16+$AK16,$S16*IFERROR(VLOOKUP($B16,'Cost Library'!$A$2:$Q$159,16,FALSE),0.1))) -> 0 | AP16: =IF($A16<>"Yes",0,$U16-$S16) -> 0 | AQ16: =IF($S16=0,0,$AM16/$S16) -> 0 | AR16: =IF($S16=0,0,$AN16/$S16) -> 0 | AS16: =IF($S16=0,0,$AO16/$S16) -> 0 | AT16: =IF($A16<>"Yes","",IF($R16="Detailed Breakdown","Detailed input",IF($R16="Contractor Quote","Estimated allocation - request vendor split","Planning allocation"))) | AU16: Typical | AV16: =IF($A16<>"Yes",0,IF($AU16="Low",$L16*$N16,IF($AU16="High",$L16*$P16,$L16*$O16))) -> 0 | AW16: =IF($A16<>"Yes",0,$AV16*(1+$T16)) -> 0 | AX16: =IF(AND($A16="Yes",$AL16>0),$AL16*(1+$T16),0) -> 0 | AY16: =IF($AX16>0,$AW16,0) -> 0 | AZ16: =IF($AX16>0,$AX16-$AY16,0) -> 0 | BA16: =IF($AY16=0,0,$AZ16/$AY16) -> 0 | BB16: =IF($A16<>"Yes","",IF($Q16>0,"Quoted",IF($AL16>0,"Detailed","Ballpark")))
A17: No | C17: =IFERROR(VLOOKUP($B17,'Cost Library'!$A$2:$M$159,2,FALSE),"") | D17: =IFERROR(VLOOKUP($B17,'Cost Library'!$A$2:$M$159,3,FALSE),"") | G17: =IFERROR(VLOOKUP($B17,'Cost Library'!$A$2:$M$159,5,FALSE),"") | L17: 1 | M17: =IFERROR(VLOOKUP($B17,'Cost Library'!$A$2:$M$159,6,FALSE),"") | N17: =IFERROR(VLOOKUP($B17,'Cost Library'!$A$2:$M$159,7,FALSE),0) -> 0 | O17: =IFERROR(VLOOKUP($B17,'Cost Library'!$A$2:$M$159,8,FALSE),0) -> 0 | P17: =IFERROR(VLOOKUP($B17,'Cost Library'!$A$2:$M$159,9,FALSE),0) -> 0 | R17: Typical | S17: =IF($A17<>"Yes",0,IF($R17="Detailed Breakdown",$AL17,IF($R17="Contractor Quote",$Q17,IF($R17="Low",$L17*$N17,IF($R17="High",$L17*$P17,$L17*$O17))))) -> 0 | T17: ='Project Inputs'!$C$15 -> 0.1 | U17: =IF($A17<>"Yes",0,$S17*(1+$T17)) -> 0 | V17: Not Started | W17: =IFERROR(VLOOKUP($B17,'Cost Library'!$A$2:$M$159,10,FALSE),"") | AF17: =IF(OR(AD17="",AE17=""),0,AD17*AE17) -> 0 | AI17: =IF(OR(AG17="",AH17=""),0,AG17*AH17) -> 0 | AL17: =SUM(AF17,AI17,AJ17,AK17) -> 0 | AM17: =IF($A17<>"Yes",0,IF($R17="Detailed Breakdown",$AF17,$S17*IFERROR(VLOOKUP($B17,'Cost Library'!$A$2:$Q$159,14,FALSE),0.4))) -> 0 | AN17: =IF($A17<>"Yes",0,IF($R17="Detailed Breakdown",$AI17,$S17*IFERROR(VLOOKUP($B17,'Cost Library'!$A$2:$Q$159,15,FALSE),0.5))) -> 0 | AO17: =IF($A17<>"Yes",0,IF($R17="Detailed Breakdown",$AJ17+$AK17,$S17*IFERROR(VLOOKUP($B17,'Cost Library'!$A$2:$Q$159,16,FALSE),0.1))) -> 0 | AP17: =IF($A17<>"Yes",0,$U17-$S17) -> 0 | AQ17: =IF($S17=0,0,$AM17/$S17) -> 0 | AR17: =IF($S17=0,0,$AN17/$S17) -> 0 | AS17: =IF($S17=0,0,$AO17/$S17) -> 0 | AT17: =IF($A17<>"Yes","",IF($R17="Detailed Breakdown","Detailed input",IF($R17="Contractor Quote","Estimated allocation - request vendor split","Planning allocation"))) | AU17: Typical | AV17: =IF($A17<>"Yes",0,IF($AU17="Low",$L17*$N17,IF($AU17="High",$L17*$P17,$L17*$O17))) -> 0 | AW17: =IF($A17<>"Yes",0,$AV17*(1+$T17)) -> 0 | AX17: =IF(AND($A17="Yes",$AL17>0),$AL17*(1+$T17),0) -> 0 | AY17: =IF($AX17>0,$AW17,0) -> 0 | AZ17: =IF($AX17>0,$AX17-$AY17,0) -> 0 | BA17: =IF($AY17=0,0,$AZ17/$AY17) -> 0 | BB17: =IF($A17<>"Yes","",IF($Q17>0,"Quoted",IF($AL17>0,"Detailed","Ballpark")))
A18: No | C18: =IFERROR(VLOOKUP($B18,'Cost Library'!$A$2:$M$159,2,FALSE),"") | D18: =IFERROR(VLOOKUP($B18,'Cost Library'!$A$2:$M$159,3,FALSE),"") | G18: =IFERROR(VLOOKUP($B18,'Cost Library'!$A$2:$M$159,5,FALSE),"") | L18: 1 | M18: =IFERROR(VLOOKUP($B18,'Cost Library'!$A$2:$M$159,6,FALSE),"") | N18: =IFERROR(VLOOKUP($B18,'Cost Library'!$A$2:$M$159,7,FALSE),0) -> 0 | O18: =IFERROR(VLOOKUP($B18,'Cost Library'!$A$2:$M$159,8,FALSE),0) -> 0 | P18: =IFERROR(VLOOKUP($B18,'Cost Library'!$A$2:$M$159,9,FALSE),0) -> 0 | R18: Typical | S18: =IF($A18<>"Yes",0,IF($R18="Detailed Breakdown",$AL18,IF($R18="Contractor Quote",$Q18,IF($R18="Low",$L18*$N18,IF($R18="High",$L18*$P18,$L18*$O18))))) -> 0 | T18: ='Project Inputs'!$C$15 -> 0.1 | U18: =IF($A18<>"Yes",0,$S18*(1+$T18)) -> 0 | V18: Not Started | W18: =IFERROR(VLOOKUP($B18,'Cost Library'!$A$2:$M$159,10,FALSE),"") | AF18: =IF(OR(AD18="",AE18=""),0,AD18*AE18) -> 0 | AI18: =IF(OR(AG18="",AH18=""),0,AG18*AH18) -> 0 | AL18: =SUM(AF18,AI18,AJ18,AK18) -> 0 | AM18: =IF($A18<>"Yes",0,IF($R18="Detailed Breakdown",$AF18,$S18*IFERROR(VLOOKUP($B18,'Cost Library'!$A$2:$Q$159,14,FALSE),0.4))) -> 0 | AN18: =IF($A18<>"Yes",0,IF($R18="Detailed Breakdown",$AI18,$S18*IFERROR(VLOOKUP($B18,'Cost Library'!$A$2:$Q$159,15,FALSE),0.5))) -> 0 | AO18: =IF($A18<>"Yes",0,IF($R18="Detailed Breakdown",$AJ18+$AK18,$S18*IFERROR(VLOOKUP($B18,'Cost Library'!$A$2:$Q$159,16,FALSE),0.1))) -> 0 | AP18: =IF($A18<>"Yes",0,$U18-$S18) -> 0 | AQ18: =IF($S18=0,0,$AM18/$S18) -> 0 | AR18: =IF($S18=0,0,$AN18/$S18) -> 0 | AS18: =IF($S18=0,0,$AO18/$S18) -> 0 | AT18: =IF($A18<>"Yes","",IF($R18="Detailed Breakdown","Detailed input",IF($R18="Contractor Quote","Estimated allocation - request vendor split","Planning allocation"))) | AU18: Typical | AV18: =IF($A18<>"Yes",0,IF($AU18="Low",$L18*$N18,IF($AU18="High",$L18*$P18,$L18*$O18))) -> 0 | AW18: =IF($A18<>"Yes",0,$AV18*(1+$T18)) -> 0 | AX18: =IF(AND($A18="Yes",$AL18>0),$AL18*(1+$T18),0) -> 0 | AY18: =IF($AX18>0,$AW18,0) -> 0 | AZ18: =IF($AX18>0,$AX18-$AY18,0) -> 0 | BA18: =IF($AY18=0,0,$AZ18/$AY18) -> 0 | BB18: =IF($A18<>"Yes","",IF($Q18>0,"Quoted",IF($AL18>0,"Detailed","Ballpark")))
A19: No | C19: =IFERROR(VLOOKUP($B19,'Cost Library'!$A$2:$M$159,2,FALSE),"") | D19: =IFERROR(VLOOKUP($B19,'Cost Library'!$A$2:$M$159,3,FALSE),"") | G19: =IFERROR(VLOOKUP($B19,'Cost Library'!$A$2:$M$159,5,FALSE),"") | L19: 1 | M19: =IFERROR(VLOOKUP($B19,'Cost Library'!$A$2:$M$159,6,FALSE),"") | N19: =IFERROR(VLOOKUP($B19,'Cost Library'!$A$2:$M$159,7,FALSE),0) -> 0 | O19: =IFERROR(VLOOKUP($B19,'Cost Library'!$A$2:$M$159,8,FALSE),0) -> 0 | P19: =IFERROR(VLOOKUP($B19,'Cost Library'!$A$2:$M$159,9,FALSE),0) -> 0 | R19: Typical | S19: =IF($A19<>"Yes",0,IF($R19="Detailed Breakdown",$AL19,IF($R19="Contractor Quote",$Q19,IF($R19="Low",$L19*$N19,IF($R19="High",$L19*$P19,$L19*$O19))))) -> 0 | T19: ='Project Inputs'!$C$15 -> 0.1 | U19: =IF($A19<>"Yes",0,$S19*(1+$T19)) -> 0 | V19: Not Started | W19: =IFERROR(VLOOKUP($B19,'Cost Library'!$A$2:$M$159,10,FALSE),"") | AF19: =IF(OR(AD19="",AE19=""),0,AD19*AE19) -> 0 | AI19: =IF(OR(AG19="",AH19=""),0,AG19*AH19) -> 0 | AL19: =SUM(AF19,AI19,AJ19,AK19) -> 0 | AM19: =IF($A19<>"Yes",0,IF($R19="Detailed Breakdown",$AF19,$S19*IFERROR(VLOOKUP($B19,'Cost Library'!$A$2:$Q$159,14,FALSE),0.4))) -> 0 | AN19: =IF($A19<>"Yes",0,IF($R19="Detailed Breakdown",$AI19,$S19*IFERROR(VLOOKUP($B19,'Cost Library'!$A$2:$Q$159,15,FALSE),0.5))) -> 0 | AO19: =IF($A19<>"Yes",0,IF($R19="Detailed Breakdown",$AJ19+$AK19,$S19*IFERROR(VLOOKUP($B19,'Cost Library'!$A$2:$Q$159,16,FALSE),0.1))) -> 0 | AP19: =IF($A19<>"Yes",0,$U19-$S19) -> 0 | AQ19: =IF($S19=0,0,$AM19/$S19) -> 0 | AR19: =IF($S19=0,0,$AN19/$S19) -> 0 | AS19: =IF($S19=0,0,$AO19/$S19) -> 0 | AT19: =IF($A19<>"Yes","",IF($R19="Detailed Breakdown","Detailed input",IF($R19="Contractor Quote","Estimated allocation - request vendor split","Planning allocation"))) | AU19: Typical | AV19: =IF($A19<>"Yes",0,IF($AU19="Low",$L19*$N19,IF($AU19="High",$L19*$P19,$L19*$O19))) -> 0 | AW19: =IF($A19<>"Yes",0,$AV19*(1+$T19)) -> 0 | AX19: =IF(AND($A19="Yes",$AL19>0),$AL19*(1+$T19),0) -> 0 | AY19: =IF($AX19>0,$AW19,0) -> 0 | AZ19: =IF($AX19>0,$AX19-$AY19,0) -> 0 | BA19: =IF($AY19=0,0,$AZ19/$AY19) -> 0 | BB19: =IF($A19<>"Yes","",IF($Q19>0,"Quoted",IF($AL19>0,"Detailed","Ballpark")))
A20: No | C20: =IFERROR(VLOOKUP($B20,'Cost Library'!$A$2:$M$159,2,FALSE),"") | D20: =IFERROR(VLOOKUP($B20,'Cost Library'!$A$2:$M$159,3,FALSE),"") | G20: =IFERROR(VLOOKUP($B20,'Cost Library'!$A$2:$M$159,5,FALSE),"") | L20: 1 | M20: =IFERROR(VLOOKUP($B20,'Cost Library'!$A$2:$M$159,6,FALSE),"") | N20: =IFERROR(VLOOKUP($B20,'Cost Library'!$A$2:$M$159,7,FALSE),0) -> 0 | O20: =IFERROR(VLOOKUP($B20,'Cost Library'!$A$2:$M$159,8,FALSE),0) -> 0 | P20: =IFERROR(VLOOKUP($B20,'Cost Library'!$A$2:$M$159,9,FALSE),0) -> 0 | R20: Typical | S20: =IF($A20<>"Yes",0,IF($R20="Detailed Breakdown",$AL20,IF($R20="Contractor Quote",$Q20,IF($R20="Low",$L20*$N20,IF($R20="High",$L20*$P20,$L20*$O20))))) -> 0 | T20: ='Project Inputs'!$C$15 -> 0.1 | U20: =IF($A20<>"Yes",0,$S20*(1+$T20)) -> 0 | V20: Not Started | W20: =IFERROR(VLOOKUP($B20,'Cost Library'!$A$2:$M$159,10,FALSE),"") | AF20: =IF(OR(AD20="",AE20=""),0,AD20*AE20) -> 0 | AI20: =IF(OR(AG20="",AH20=""),0,AG20*AH20) -> 0 | AL20: =SUM(AF20,AI20,AJ20,AK20) -> 0 | AM20: =IF($A20<>"Yes",0,IF($R20="Detailed Breakdown",$AF20,$S20*IFERROR(VLOOKUP($B20,'Cost Library'!$A$2:$Q$159,14,FALSE),0.4))) -> 0 | AN20: =IF($A20<>"Yes",0,IF($R20="Detailed Breakdown",$AI20,$S20*IFERROR(VLOOKUP($B20,'Cost Library'!$A$2:$Q$159,15,FALSE),0.5))) -> 0 | AO20: =IF($A20<>"Yes",0,IF($R20="Detailed Breakdown",$AJ20+$AK20,$S20*IFERROR(VLOOKUP($B20,'Cost Library'!$A$2:$Q$159,16,FALSE),0.1))) -> 0 | AP20: =IF($A20<>"Yes",0,$U20-$S20) -> 0 | AQ20: =IF($S20=0,0,$AM20/$S20) -> 0 | AR20: =IF($S20=0,0,$AN20/$S20) -> 0 | AS20: =IF($S20=0,0,$AO20/$S20) -> 0 | AT20: =IF($A20<>"Yes","",IF($R20="Detailed Breakdown","Detailed input",IF($R20="Contractor Quote","Estimated allocation - request vendor split","Planning allocation"))) | AU20: Typical | AV20: =IF($A20<>"Yes",0,IF($AU20="Low",$L20*$N20,IF($AU20="High",$L20*$P20,$L20*$O20))) -> 0 | AW20: =IF($A20<>"Yes",0,$AV20*(1+$T20)) -> 0 | AX20: =IF(AND($A20="Yes",$AL20>0),$AL20*(1+$T20),0) -> 0 | AY20: =IF($AX20>0,$AW20,0) -> 0 | AZ20: =IF($AX20>0,$AX20-$AY20,0) -> 0 | BA20: =IF($AY20=0,0,$AZ20/$AY20) -> 0 | BB20: =IF($A20<>"Yes","",IF($Q20>0,"Quoted",IF($AL20>0,"Detailed","Ballpark")))
A21: No | C21: =IFERROR(VLOOKUP($B21,'Cost Library'!$A$2:$M$159,2,FALSE),"") | D21: =IFERROR(VLOOKUP($B21,'Cost Library'!$A$2:$M$159,3,FALSE),"") | G21: =IFERROR(VLOOKUP($B21,'Cost Library'!$A$2:$M$159,5,FALSE),"") | L21: 1 | M21: =IFERROR(VLOOKUP($B21,'Cost Library'!$A$2:$M$159,6,FALSE),"") | N21: =IFERROR(VLOOKUP($B21,'Cost Library'!$A$2:$M$159,7,FALSE),0) -> 0 | O21: =IFERROR(VLOOKUP($B21,'Cost Library'!$A$2:$M$159,8,FALSE),0) -> 0 | P21: =IFERROR(VLOOKUP($B21,'Cost Library'!$A$2:$M$159,9,FALSE),0) -> 0 | R21: Typical | S21: =IF($A21<>"Yes",0,IF($R21="Detailed Breakdown",$AL21,IF($R21="Contractor Quote",$Q21,IF($R21="Low",$L21*$N21,IF($R21="High",$L21*$P21,$L21*$O21))))) -> 0 | T21: ='Project Inputs'!$C$15 -> 0.1 | U21: =IF($A21<>"Yes",0,$S21*(1+$T21)) -> 0 | V21: Not Started | W21: =IFERROR(VLOOKUP($B21,'Cost Library'!$A$2:$M$159,10,FALSE),"") | AF21: =IF(OR(AD21="",AE21=""),0,AD21*AE21) -> 0 | AI21: =IF(OR(AG21="",AH21=""),0,AG21*AH21) -> 0 | AL21: =SUM(AF21,AI21,AJ21,AK21) -> 0 | AM21: =IF($A21<>"Yes",0,IF($R21="Detailed Breakdown",$AF21,$S21*IFERROR(VLOOKUP($B21,'Cost Library'!$A$2:$Q$159,14,FALSE),0.4))) -> 0 | AN21: =IF($A21<>"Yes",0,IF($R21="Detailed Breakdown",$AI21,$S21*IFERROR(VLOOKUP($B21,'Cost Library'!$A$2:$Q$159,15,FALSE),0.5))) -> 0 | AO21: =IF($A21<>"Yes",0,IF($R21="Detailed Breakdown",$AJ21+$AK21,$S21*IFERROR(VLOOKUP($B21,'Cost Library'!$A$2:$Q$159,16,FALSE),0.1))) -> 0 | AP21: =IF($A21<>"Yes",0,$U21-$S21) -> 0 | AQ21: =IF($S21=0,0,$AM21/$S21) -> 0 | AR21: =IF($S21=0,0,$AN21/$S21) -> 0 | AS21: =IF($S21=0,0,$AO21/$S21) -> 0 | AT21: =IF($A21<>"Yes","",IF($R21="Detailed Breakdown","Detailed input",IF($R21="Contractor Quote","Estimated allocation - request vendor split","Planning allocation"))) | AU21: Typical | AV21: =IF($A21<>"Yes",0,IF($AU21="Low",$L21*$N21,IF($AU21="High",$L21*$P21,$L21*$O21))) -> 0 | AW21: =IF($A21<>"Yes",0,$AV21*(1+$T21)) -> 0 | AX21: =IF(AND($A21="Yes",$AL21>0),$AL21*(1+$T21),0) -> 0 | AY21: =IF($AX21>0,$AW21,0) -> 0 | AZ21: =IF($AX21>0,$AX21-$AY21,0) -> 0 | BA21: =IF($AY21=0,0,$AZ21/$AY21) -> 0 | BB21: =IF($A21<>"Yes","",IF($Q21>0,"Quoted",IF($AL21>0,"Detailed","Ballpark")))
A22: No | C22: =IFERROR(VLOOKUP($B22,'Cost Library'!$A$2:$M$159,2,FALSE),"") | D22: =IFERROR(VLOOKUP($B22,'Cost Library'!$A$2:$M$159,3,FALSE),"") | G22: =IFERROR(VLOOKUP($B22,'Cost Library'!$A$2:$M$159,5,FALSE),"") | L22: 1 | M22: =IFERROR(VLOOKUP($B22,'Cost Library'!$A$2:$M$159,6,FALSE),"") | N22: =IFERROR(VLOOKUP($B22,'Cost Library'!$A$2:$M$159,7,FALSE),0) -> 0 | O22: =IFERROR(VLOOKUP($B22,'Cost Library'!$A$2:$M$159,8,FALSE),0) -> 0 | P22: =IFERROR(VLOOKUP($B22,'Cost Library'!$A$2:$M$159,9,FALSE),0) -> 0 | R22: Typical | S22: =IF($A22<>"Yes",0,IF($R22="Detailed Breakdown",$AL22,IF($R22="Contractor Quote",$Q22,IF($R22="Low",$L22*$N22,IF($R22="High",$L22*$P22,$L22*$O22))))) -> 0 | T22: ='Project Inputs'!$C$15 -> 0.1 | U22: =IF($A22<>"Yes",0,$S22*(1+$T22)) -> 0 | V22: Not Started | W22: =IFERROR(VLOOKUP($B22,'Cost Library'!$A$2:$M$159,10,FALSE),"") | AF22: =IF(OR(AD22="",AE22=""),0,AD22*AE22) -> 0 | AI22: =IF(OR(AG22="",AH22=""),0,AG22*AH22) -> 0 | AL22: =SUM(AF22,AI22,AJ22,AK22) -> 0 | AM22: =IF($A22<>"Yes",0,IF($R22="Detailed Breakdown",$AF22,$S22*IFERROR(VLOOKUP($B22,'Cost Library'!$A$2:$Q$159,14,FALSE),0.4))) -> 0 | AN22: =IF($A22<>"Yes",0,IF($R22="Detailed Breakdown",$AI22,$S22*IFERROR(VLOOKUP($B22,'Cost Library'!$A$2:$Q$159,15,FALSE),0.5))) -> 0 | AO22: =IF($A22<>"Yes",0,IF($R22="Detailed Breakdown",$AJ22+$AK22,$S22*IFERROR(VLOOKUP($B22,'Cost Library'!$A$2:$Q$159,16,FALSE),0.1))) -> 0 | AP22: =IF($A22<>"Yes",0,$U22-$S22) -> 0 | AQ22: =IF($S22=0,0,$AM22/$S22) -> 0 | AR22: =IF($S22=0,0,$AN22/$S22) -> 0 | AS22: =IF($S22=0,0,$AO22/$S22) -> 0 | AT22: =IF($A22<>"Yes","",IF($R22="Detailed Breakdown","Detailed input",IF($R22="Contractor Quote","Estimated allocation - request vendor split","Planning allocation"))) | AU22: Typical | AV22: =IF($A22<>"Yes",0,IF($AU22="Low",$L22*$N22,IF($AU22="High",$L22*$P22,$L22*$O22))) -> 0 | AW22: =IF($A22<>"Yes",0,$AV22*(1+$T22)) -> 0 | AX22: =IF(AND($A22="Yes",$AL22>0),$AL22*(1+$T22),0) -> 0 | AY22: =IF($AX22>0,$AW22,0) -> 0 | AZ22: =IF($AX22>0,$AX22-$AY22,0) -> 0 | BA22: =IF($AY22=0,0,$AZ22/$AY22) -> 0 | BB22: =IF($A22<>"Yes","",IF($Q22>0,"Quoted",IF($AL22>0,"Detailed","Ballpark")))
A23: No | C23: =IFERROR(VLOOKUP($B23,'Cost Library'!$A$2:$M$159,2,FALSE),"") | D23: =IFERROR(VLOOKUP($B23,'Cost Library'!$A$2:$M$159,3,FALSE),"") | G23: =IFERROR(VLOOKUP($B23,'Cost Library'!$A$2:$M$159,5,FALSE),"") | L23: 1 | M23: =IFERROR(VLOOKUP($B23,'Cost Library'!$A$2:$M$159,6,FALSE),"") | N23: =IFERROR(VLOOKUP($B23,'Cost Library'!$A$2:$M$159,7,FALSE),0) -> 0 | O23: =IFERROR(VLOOKUP($B23,'Cost Library'!$A$2:$M$159,8,FALSE),0) -> 0 | P23: =IFERROR(VLOOKUP($B23,'Cost Library'!$A$2:$M$159,9,FALSE),0) -> 0 | R23: Typical | S23: =IF($A23<>"Yes",0,IF($R23="Detailed Breakdown",$AL23,IF($R23="Contractor Quote",$Q23,IF($R23="Low",$L23*$N23,IF($R23="High",$L23*$P23,$L23*$O23))))) -> 0 | T23: ='Project Inputs'!$C$15 -> 0.1 | U23: =IF($A23<>"Yes",0,$S23*(1+$T23)) -> 0 | V23: Not Started | W23: =IFERROR(VLOOKUP($B23,'Cost Library'!$A$2:$M$159,10,FALSE),"") | AF23: =IF(OR(AD23="",AE23=""),0,AD23*AE23) -> 0 | AI23: =IF(OR(AG23="",AH23=""),0,AG23*AH23) -> 0 | AL23: =SUM(AF23,AI23,AJ23,AK23) -> 0 | AM23: =IF($A23<>"Yes",0,IF($R23="Detailed Breakdown",$AF23,$S23*IFERROR(VLOOKUP($B23,'Cost Library'!$A$2:$Q$159,14,FALSE),0.4))) -> 0 | AN23: =IF($A23<>"Yes",0,IF($R23="Detailed Breakdown",$AI23,$S23*IFERROR(VLOOKUP($B23,'Cost Library'!$A$2:$Q$159,15,FALSE),0.5))) -> 0 | AO23: =IF($A23<>"Yes",0,IF($R23="Detailed Breakdown",$AJ23+$AK23,$S23*IFERROR(VLOOKUP($B23,'Cost Library'!$A$2:$Q$159,16,FALSE),0.1))) -> 0 | AP23: =IF($A23<>"Yes",0,$U23-$S23) -> 0 | AQ23: =IF($S23=0,0,$AM23/$S23) -> 0 | AR23: =IF($S23=0,0,$AN23/$S23) -> 0 | AS23: =IF($S23=0,0,$AO23/$S23) -> 0 | AT23: =IF($A23<>"Yes","",IF($R23="Detailed Breakdown","Detailed input",IF($R23="Contractor Quote","Estimated allocation - request vendor split","Planning allocation"))) | AU23: Typical | AV23: =IF($A23<>"Yes",0,IF($AU23="Low",$L23*$N23,IF($AU23="High",$L23*$P23,$L23*$O23))) -> 0 | AW23: =IF($A23<>"Yes",0,$AV23*(1+$T23)) -> 0 | AX23: =IF(AND($A23="Yes",$AL23>0),$AL23*(1+$T23),0) -> 0 | AY23: =IF($AX23>0,$AW23,0) -> 0 | AZ23: =IF($AX23>0,$AX23-$AY23,0) -> 0 | BA23: =IF($AY23=0,0,$AZ23/$AY23) -> 0 | BB23: =IF($A23<>"Yes","",IF($Q23>0,"Quoted",IF($AL23>0,"Detailed","Ballpark")))
A24: No | C24: =IFERROR(VLOOKUP($B24,'Cost Library'!$A$2:$M$159,2,FALSE),"") | D24: =IFERROR(VLOOKUP($B24,'Cost Library'!$A$2:$M$159,3,FALSE),"") | G24: =IFERROR(VLOOKUP($B24,'Cost Library'!$A$2:$M$159,5,FALSE),"") | L24: 1 | M24: =IFERROR(VLOOKUP($B24,'Cost Library'!$A$2:$M$159,6,FALSE),"") | N24: =IFERROR(VLOOKUP($B24,'Cost Library'!$A$2:$M$159,7,FALSE),0) -> 0 | O24: =IFERROR(VLOOKUP($B24,'Cost Library'!$A$2:$M$159,8,FALSE),0) -> 0 | P24: =IFERROR(VLOOKUP($B24,'Cost Library'!$A$2:$M$159,9,FALSE),0) -> 0 | R24: Typical | S24: =IF($A24<>"Yes",0,IF($R24="Detailed Breakdown",$AL24,IF($R24="Contractor Quote",$Q24,IF($R24="Low",$L24*$N24,IF($R24="High",$L24*$P24,$L24*$O24))))) -> 0 | T24: ='Project Inputs'!$C$15 -> 0.1 | U24: =IF($A24<>"Yes",0,$S24*(1+$T24)) -> 0 | V24: Not Started | W24: =IFERROR(VLOOKUP($B24,'Cost Library'!$A$2:$M$159,10,FALSE),"") | AF24: =IF(OR(AD24="",AE24=""),0,AD24*AE24) -> 0 | AI24: =IF(OR(AG24="",AH24=""),0,AG24*AH24) -> 0 | AL24: =SUM(AF24,AI24,AJ24,AK24) -> 0 | AM24: =IF($A24<>"Yes",0,IF($R24="Detailed Breakdown",$AF24,$S24*IFERROR(VLOOKUP($B24,'Cost Library'!$A$2:$Q$159,14,FALSE),0.4))) -> 0 | AN24: =IF($A24<>"Yes",0,IF($R24="Detailed Breakdown",$AI24,$S24*IFERROR(VLOOKUP($B24,'Cost Library'!$A$2:$Q$159,15,FALSE),0.5))) -> 0 | AO24: =IF($A24<>"Yes",0,IF($R24="Detailed Breakdown",$AJ24+$AK24,$S24*IFERROR(VLOOKUP($B24,'Cost Library'!$A$2:$Q$159,16,FALSE),0.1))) -> 0 | AP24: =IF($A24<>"Yes",0,$U24-$S24) -> 0 | AQ24: =IF($S24=0,0,$AM24/$S24) -> 0 | AR24: =IF($S24=0,0,$AN24/$S24) -> 0 | AS24: =IF($S24=0,0,$AO24/$S24) -> 0 | AT24: =IF($A24<>"Yes","",IF($R24="Detailed Breakdown","Detailed input",IF($R24="Contractor Quote","Estimated allocation - request vendor split","Planning allocation"))) | AU24: Typical | AV24: =IF($A24<>"Yes",0,IF($AU24="Low",$L24*$N24,IF($AU24="High",$L24*$P24,$L24*$O24))) -> 0 | AW24: =IF($A24<>"Yes",0,$AV24*(1+$T24)) -> 0 | AX24: =IF(AND($A24="Yes",$AL24>0),$AL24*(1+$T24),0) -> 0 | AY24: =IF($AX24>0,$AW24,0) -> 0 | AZ24: =IF($AX24>0,$AX24-$AY24,0) -> 0 | BA24: =IF($AY24=0,0,$AZ24/$AY24) -> 0 | BB24: =IF($A24<>"Yes","",IF($Q24>0,"Quoted",IF($AL24>0,"Detailed","Ballpark")))
A25: No | C25: =IFERROR(VLOOKUP($B25,'Cost Library'!$A$2:$M$159,2,FALSE),"") | D25: =IFERROR(VLOOKUP($B25,'Cost Library'!$A$2:$M$159,3,FALSE),"") | G25: =IFERROR(VLOOKUP($B25,'Cost Library'!$A$2:$M$159,5,FALSE),"") | L25: 1 | M25: =IFERROR(VLOOKUP($B25,'Cost Library'!$A$2:$M$159,6,FALSE),"") | N25: =IFERROR(VLOOKUP($B25,'Cost Library'!$A$2:$M$159,7,FALSE),0) -> 0 | O25: =IFERROR(VLOOKUP($B25,'Cost Library'!$A$2:$M$159,8,FALSE),0) -> 0 | P25: =IFERROR(VLOOKUP($B25,'Cost Library'!$A$2:$M$159,9,FALSE),0) -> 0 | R25: Typical | S25: =IF($A25<>"Yes",0,IF($R25="Detailed Breakdown",$AL25,IF($R25="Contractor Quote",$Q25,IF($R25="Low",$L25*$N25,IF($R25="High",$L25*$P25,$L25*$O25))))) -> 0 | T25: ='Project Inputs'!$C$15 -> 0.1 | U25: =IF($A25<>"Yes",0,$S25*(1+$T25)) -> 0 | V25: Not Started | W25: =IFERROR(VLOOKUP($B25,'Cost Library'!$A$2:$M$159,10,FALSE),"") | AF25: =IF(OR(AD25="",AE25=""),0,AD25*AE25) -> 0 | AI25: =IF(OR(AG25="",AH25=""),0,AG25*AH25) -> 0 | AL25: =SUM(AF25,AI25,AJ25,AK25) -> 0 | AM25: =IF($A25<>"Yes",0,IF($R25="Detailed Breakdown",$AF25,$S25*IFERROR(VLOOKUP($B25,'Cost Library'!$A$2:$Q$159,14,FALSE),0.4))) -> 0 | AN25: =IF($A25<>"Yes",0,IF($R25="Detailed Breakdown",$AI25,$S25*IFERROR(VLOOKUP($B25,'Cost Library'!$A$2:$Q$159,15,FALSE),0.5))) -> 0 | AO25: =IF($A25<>"Yes",0,IF($R25="Detailed Breakdown",$AJ25+$AK25,$S25*IFERROR(VLOOKUP($B25,'Cost Library'!$A$2:$Q$159,16,FALSE),0.1))) -> 0 | AP25: =IF($A25<>"Yes",0,$U25-$S25) -> 0 | AQ25: =IF($S25=0,0,$AM25/$S25) -> 0 | AR25: =IF($S25=0,0,$AN25/$S25) -> 0 | AS25: =IF($S25=0,0,$AO25/$S25) -> 0 | AT25: =IF($A25<>"Yes","",IF($R25="Detailed Breakdown","Detailed input",IF($R25="Contractor Quote","Estimated allocation - request vendor split","Planning allocation"))) | AU25: Typical | AV25: =IF($A25<>"Yes",0,IF($AU25="Low",$L25*$N25,IF($AU25="High",$L25*$P25,$L25*$O25))) -> 0 | AW25: =IF($A25<>"Yes",0,$AV25*(1+$T25)) -> 0 | AX25: =IF(AND($A25="Yes",$AL25>0),$AL25*(1+$T25),0) -> 0 | AY25: =IF($AX25>0,$AW25,0) -> 0 | AZ25: =IF($AX25>0,$AX25-$AY25,0) -> 0 | BA25: =IF($AY25=0,0,$AZ25/$AY25) -> 0 | BB25: =IF($A25<>"Yes","",IF($Q25>0,"Quoted",IF($AL25>0,"Detailed","Ballpark")))
A26: No | C26: =IFERROR(VLOOKUP($B26,'Cost Library'!$A$2:$M$159,2,FALSE),"") | D26: =IFERROR(VLOOKUP($B26,'Cost Library'!$A$2:$M$159,3,FALSE),"") | G26: =IFERROR(VLOOKUP($B26,'Cost Library'!$A$2:$M$159,5,FALSE),"") | L26: 1 | M26: =IFERROR(VLOOKUP($B26,'Cost Library'!$A$2:$M$159,6,FALSE),"") | N26: =IFERROR(VLOOKUP($B26,'Cost Library'!$A$2:$M$159,7,FALSE),0) -> 0 | O26: =IFERROR(VLOOKUP($B26,'Cost Library'!$A$2:$M$159,8,FALSE),0) -> 0 | P26: =IFERROR(VLOOKUP($B26,'Cost Library'!$A$2:$M$159,9,FALSE),0) -> 0 | R26: Typical | S26: =IF($A26<>"Yes",0,IF($R26="Detailed Breakdown",$AL26,IF($R26="Contractor Quote",$Q26,IF($R26="Low",$L26*$N26,IF($R26="High",$L26*$P26,$L26*$O26))))) -> 0 | T26: ='Project Inputs'!$C$15 -> 0.1 | U26: =IF($A26<>"Yes",0,$S26*(1+$T26)) -> 0 | V26: Not Started | W26: =IFERROR(VLOOKUP($B26,'Cost Library'!$A$2:$M$159,10,FALSE),"") | AF26: =IF(OR(AD26="",AE26=""),0,AD26*AE26) -> 0 | AI26: =IF(OR(AG26="",AH26=""),0,AG26*AH26) -> 0 | AL26: =SUM(AF26,AI26,AJ26,AK26) -> 0 | AM26: =IF($A26<>"Yes",0,IF($R26="Detailed Breakdown",$AF26,$S26*IFERROR(VLOOKUP($B26,'Cost Library'!$A$2:$Q$159,14,FALSE),0.4))) -> 0 | AN26: =IF($A26<>"Yes",0,IF($R26="Detailed Breakdown",$AI26,$S26*IFERROR(VLOOKUP($B26,'Cost Library'!$A$2:$Q$159,15,FALSE),0.5))) -> 0 | AO26: =IF($A26<>"Yes",0,IF($R26="Detailed Breakdown",$AJ26+$AK26,$S26*IFERROR(VLOOKUP($B26,'Cost Library'!$A$2:$Q$159,16,FALSE),0.1))) -> 0 | AP26: =IF($A26<>"Yes",0,$U26-$S26) -> 0 | AQ26: =IF($S26=0,0,$AM26/$S26) -> 0 | AR26: =IF($S26=0,0,$AN26/$S26) -> 0 | AS26: =IF($S26=0,0,$AO26/$S26) -> 0 | AT26: =IF($A26<>"Yes","",IF($R26="Detailed Breakdown","Detailed input",IF($R26="Contractor Quote","Estimated allocation - request vendor split","Planning allocation"))) | AU26: Typical | AV26: =IF($A26<>"Yes",0,IF($AU26="Low",$L26*$N26,IF($AU26="High",$L26*$P26,$L26*$O26))) -> 0 | AW26: =IF($A26<>"Yes",0,$AV26*(1+$T26)) -> 0 | AX26: =IF(AND($A26="Yes",$AL26>0),$AL26*(1+$T26),0) -> 0 | AY26: =IF($AX26>0,$AW26,0) -> 0 | AZ26: =IF($AX26>0,$AX26-$AY26,0) -> 0 | BA26: =IF($AY26=0,0,$AZ26/$AY26) -> 0 | BB26: =IF($A26<>"Yes","",IF($Q26>0,"Quoted",IF($AL26>0,"Detailed","Ballpark")))
A27: No | C27: =IFERROR(VLOOKUP($B27,'Cost Library'!$A$2:$M$159,2,FALSE),"") | D27: =IFERROR(VLOOKUP($B27,'Cost Library'!$A$2:$M$159,3,FALSE),"") | G27: =IFERROR(VLOOKUP($B27,'Cost Library'!$A$2:$M$159,5,FALSE),"") | L27: 1 | M27: =IFERROR(VLOOKUP($B27,'Cost Library'!$A$2:$M$159,6,FALSE),"") | N27: =IFERROR(VLOOKUP($B27,'Cost Library'!$A$2:$M$159,7,FALSE),0) -> 0 | O27: =IFERROR(VLOOKUP($B27,'Cost Library'!$A$2:$M$159,8,FALSE),0) -> 0 | P27: =IFERROR(VLOOKUP($B27,'Cost Library'!$A$2:$M$159,9,FALSE),0) -> 0 | R27: Typical | S27: =IF($A27<>"Yes",0,IF($R27="Detailed Breakdown",$AL27,IF($R27="Contractor Quote",$Q27,IF($R27="Low",$L27*$N27,IF($R27="High",$L27*$P27,$L27*$O27))))) -> 0 | T27: ='Project Inputs'!$C$15 -> 0.1 | U27: =IF($A27<>"Yes",0,$S27*(1+$T27)) -> 0 | V27: Not Started | W27: =IFERROR(VLOOKUP($B27,'Cost Library'!$A$2:$M$159,10,FALSE),"") | AF27: =IF(OR(AD27="",AE27=""),0,AD27*AE27) -> 0 | AI27: =IF(OR(AG27="",AH27=""),0,AG27*AH27) -> 0 | AL27: =SUM(AF27,AI27,AJ27,AK27) -> 0 | AM27: =IF($A27<>"Yes",0,IF($R27="Detailed Breakdown",$AF27,$S27*IFERROR(VLOOKUP($B27,'Cost Library'!$A$2:$Q$159,14,FALSE),0.4))) -> 0 | AN27: =IF($A27<>"Yes",0,IF($R27="Detailed Breakdown",$AI27,$S27*IFERROR(VLOOKUP($B27,'Cost Library'!$A$2:$Q$159,15,FALSE),0.5))) -> 0 | AO27: =IF($A27<>"Yes",0,IF($R27="Detailed Breakdown",$AJ27+$AK27,$S27*IFERROR(VLOOKUP($B27,'Cost Library'!$A$2:$Q$159,16,FALSE),0.1))) -> 0 | AP27: =IF($A27<>"Yes",0,$U27-$S27) -> 0 | AQ27: =IF($S27=0,0,$AM27/$S27) -> 0 | AR27: =IF($S27=0,0,$AN27/$S27) -> 0 | AS27: =IF($S27=0,0,$AO27/$S27) -> 0 | AT27: =IF($A27<>"Yes","",IF($R27="Detailed Breakdown","Detailed input",IF($R27="Contractor Quote","Estimated allocation - request vendor split","Planning allocation"))) | AU27: Typical | AV27: =IF($A27<>"Yes",0,IF($AU27="Low",$L27*$N27,IF($AU27="High",$L27*$P27,$L27*$O27))) -> 0 | AW27: =IF($A27<>"Yes",0,$AV27*(1+$T27)) -> 0 | AX27: =IF(AND($A27="Yes",$AL27>0),$AL27*(1+$T27),0) -> 0 | AY27: =IF($AX27>0,$AW27,0) -> 0 | AZ27: =IF($AX27>0,$AX27-$AY27,0) -> 0 | BA27: =IF($AY27=0,0,$AZ27/$AY27) -> 0 | BB27: =IF($A27<>"Yes","",IF($Q27>0,"Quoted",IF($AL27>0,"Detailed","Ballpark")))
... A251: No | C251: =IFERROR(VLOOKUP($B251,'Cost Library'!$A$2:$M$159,2,FALSE),"") | D251: =IFERROR(VLOOKUP($B251,'Cost Library'!$A$2:$M$159,3,FALSE),"") | G251: =IFERROR(VLOOKUP($B251,'Cost Library'!$A$2:$M$159,5,FALSE),"") | L251: 1 | M251: =IFERROR(VLOOKUP($B251,'Cost Library'!$A$2:$M$159,6,FALSE),"") | N251: =IFERROR(VLOOKUP($B251,'Cost Library'!$A$2:$M$159,7,FALSE),0) -> 0 | O251: =IFERROR(VLOOKUP($B251,'Cost Library'!$A$2:$M$159,8,FALSE),0) -> 0 | P251: =IFERROR(VLOOKUP($B251,'Cost Library'!$A$2:$M$159,9,FALSE),0) -> 0 | R251: Typical | S251: =IF($A251<>"Yes",0,IF($R251="Detailed Breakdown",$AL251,IF($R251="Contractor Quote",$Q251,IF($R251="Low",$L251*$N251,IF($R251="High",$L251*$P251,$L251*$O251))))) -> 0 | T251: ='Project Inputs'!$C$15 -> 0.1 | U251: =IF($A251<>"Yes",0,$S251*(1+$T251)) -> 0 | V251: Not Started | W251: =IFERROR(VLOOKUP($B251,'Cost Library'!$A$2:$M$159,10,FALSE),"") | AF251: =IF(OR(AD251="",AE251=""),0,AD251*AE251) -> 0 | AI251: =IF(OR(AG251="",AH251=""),0,AG251*AH251) -> 0 | AL251: =SUM(AF251,AI251,AJ251,AK251) -> 0 | AM251: =IF($A251<>"Yes",0,IF($R251="Detailed Breakdown",$AF251,$S251*IFERROR(VLOOKUP($B251,'Cost Library'!$A$2:$Q$159,14,FALSE),0.4))) -> 0 | AN251: =IF($A251<>"Yes",0,IF($R251="Detailed Breakdown",$AI251,$S251*IFERROR(VLOOKUP($B251,'Cost Library'!$A$2:$Q$159,15,FALSE),0.5))) -> 0 | AO251: =IF($A251<>"Yes",0,IF($R251="Detailed Breakdown",$AJ251+$AK251,$S251*IFERROR(VLOOKUP($B251,'Cost Library'!$A$2:$Q$159,16,FALSE),0.1))) -> 0 | AP251: =IF($A251<>"Yes",0,$U251-$S251) -> 0 | AQ251: =IF($S251=0,0,$AM251/$S251) -> 0 | AR251: =IF($S251=0,0,$AN251/$S251) -> 0 | AS251: =IF($S251=0,0,$AO251/$S251) -> 0 | AT251: =IF($A251<>"Yes","",IF($R251="Detailed Breakdown","Detailed input",IF($R251="Contractor Quote","Estimated allocation - request vendor split","Planning allocation"))) | AU251: Typical | AV251: =IF($A251<>"Yes",0,IF($AU251="Low",$L251*$N251,IF($AU251="High",$L251*$P251,$L251*$O251))) -> 0 | AW251: =IF($A251<>"Yes",0,$AV251*(1+$T251)) -> 0 | AX251: =IF(AND($A251="Yes",$AL251>0),$AL251*(1+$T251),0) -> 0 | AY251: =IF($AX251>0,$AW251,0) -> 0 | AZ251: =IF($AX251>0,$AX251-$AY251,0) -> 0 | BA251: =IF($AY251=0,0,$AZ251/$AY251) -> 0 | BB251: =IF($A251<>"Yes","",IF($Q251>0,"Quoted",IF($AL251>0,"Detailed","Ballpark")))

Sheet Cost Library
A1: Cost Code | B1: Category | C1: Trade | D1: Scope Item | E1: Work Type | F1: Unit | G1: Low Allowance | H1: Typical Allowance | I1: High Allowance | J1: Permit? | K1: Risk Class | L1: Source Basis | M1: Source URL | N1: Default Material % | O1: Default Labor % | P1: Default Other % | Q1: Cost Split Basis
A2: STR-001 | B2: Structure & Foundation | C2: Structural Engineer | D2: Structural engineer evaluation | E2: Inspection | F2: project | G2: 400 | H2: 750 | I2: 1200 | J2: No | K2: Critical | L2: 2026 foundation repair guide + rehab planning allowance; verify with local bid | M2: https://www.angi.com/articles/how-much-does-foundation-repair-cost.htm | N2: 0 | O2: 0 | P2: 1 | Q2: Inspection/professional fee classified as Other
A3: STR-002 | B3: Structure & Foundation | C3: Foundation | D3: Epoxy repair of non-structural foundation crack | E3: Repair | F3: each | G3: 300 | H3: 550 | I3: 900 | J3: Sometimes | K3: High | L3: 2026 foundation repair guide + rehab planning allowance; verify with local bid | M3: https://www.angi.com/articles/how-much-does-foundation-repair-cost.htm | N3: 0.35 | O3: 0.5 | P3: 0.15 | Q3: Heavy repair planning split
A4: STR-003 | B4: Structure & Foundation | C4: Foundation | D4: Foundation stabilization / wall bracing | E4: Repair | F4: project | G4: 2500 | H4: 7000 | I4: 15000 | J4: Yes | K4: Critical | L4: 2026 foundation repair guide + rehab planning allowance; verify with local bid | M4: https://www.angi.com/articles/how-much-does-foundation-repair-cost.htm | N4: 0.35 | O4: 0.5 | P4: 0.15 | Q4: Heavy repair planning split
A5: STR-004 | B5: Structure & Foundation | C5: Foundation | D5: Foundation pier / underpinning | E5: Repair | F5: each | G5: 1000 | H5: 1800 | I5: 3000 | J5: Yes | K5: Critical | L5: 2026 foundation repair guide + rehab planning allowance; verify with local bid | M5: https://www.angi.com/articles/how-much-does-foundation-repair-cost.htm | N5: 0.35 | O5: 0.5 | P5: 0.15 | Q5: Heavy repair planning split
A6: STR-005 | B6: Structure & Foundation | C6: Carpentry | D6: Repair damaged floor joist | E6: Repair | F6: each | G6: 300 | H6: 800 | I6: 2000 | J6: Sometimes | K6: High | L6: 2026 St. Louis whole-house renovation guide + rehab planning allowance; verify with local bid | M6: https://www.angi.com/articles/complete-house-renovation-cost/mo/st-louis | N6: 0.45 | O6: 0.45 | P6: 0.1 | Q6: Installed building component planning split
A7: STR-006 | B7: Structure & Foundation | C7: Carpentry | D7: Sister / reinforce floor joists | E7: Repair | F7: lf | G7: 15 | H7: 35 | I7: 75 | J7: Sometimes | K7: High | L7: 2026 St. Louis whole-house renovation guide + rehab planning allowance; verify with local bid | M7: https://www.angi.com/articles/complete-house-renovation-cost/mo/st-louis | N7: 0.45 | O7: 0.45 | P7: 0.1 | Q7: Installed building component planning split
A8: STR-007 | B8: Structure & Foundation | C8: Carpentry | D8: Replace structural beam/header | E8: Replace | F8: each | G8: 1500 | H8: 4000 | I8: 9000 | J8: Yes | K8: Critical | L8: 2026 St. Louis whole-house renovation guide + rehab planning allowance; verify with local bid | M8: https://www.angi.com/articles/complete-house-renovation-cost/mo/st-louis | N8: 0.45 | O8: 0.45 | P8: 0.1 | Q8: Installed building component planning split
A9: STR-008 | B9: Structure & Foundation | C9: Masonry | D9: Repair bowed/block basement wall | E9: Repair | F9: project | G9: 2500 | H9: 6500 | I9: 14000 | J9: Yes | K9: Critical | L9: 2026 foundation repair guide + rehab planning allowance; verify with local bid | M9: https://www.angi.com/articles/how-much-does-foundation-repair-cost.htm | N9: 0.35 | O9: 0.5 | P9: 0.15 | Q9: Heavy repair planning split
A10: STR-009 | B10: Structure & Foundation | C10: Waterproofing | D10: Basement waterproofing / drainage system | E10: Repair | F10: project | G10: 3000 | H10: 7000 | I10: 15000 | J10: Sometimes | K10: High | L10: 2026 foundation repair guide + rehab planning allowance; verify with local bid | M10: https://www.angi.com/articles/how-much-does-foundation-repair-cost.htm | N10: 0.45 | O10: 0.45 | P10: 0.1 | Q10: Roofing planning split
A11: STR-010 | B11: Structure & Foundation | C11: Waterproofing | D11: Crawl-space vapor barrier | E11: Repair | F11: sf | G11: 2 | H11: 4 | I11: 7 | J11: Sometimes | K11: Medium | L11: 2026 foundation repair guide + rehab planning allowance; verify with local bid | M11: https://www.angi.com/articles/how-much-does-foundation-repair-cost.htm | N11: 0.45 | O11: 0.45 | P11: 0.1 | Q11: Roofing planning split
A12: STR-011 | B12: Structure & Foundation | C12: Waterproofing | D12: Install/replace sump pump | E12: Replace | F12: each | G12: 800 | H12: 1400 | I12: 2500 | J12: Sometimes | K12: High | L12: 2026 foundation repair guide + rehab planning allowance; verify with local bid | M12: https://www.angi.com/articles/how-much-does-foundation-repair-cost.htm | N12: 0.45 | O12: 0.45 | P12: 0.1 | Q12: Roofing planning split
A13: ROF-001 | B13: Roof & Attic | C13: Roofing | D13: Full asphalt-shingle roof replacement | E13: Replace | F13: project | G13: 5433 | H13: 8155 | I13: 11032 | J13: Yes | K13: Critical | L13: 2026 St. Louis roof replacement guide | M13: https://www.angi.com/articles/how-much-does-roof-replacement-cost/mo/st-louis | N13: 0.45 | O13: 0.45 | P13: 0.1 | Q13: Roofing planning split
... A159: SOFT-010 | B159: Soft Costs & Due Diligence | C159: Photography | D159: Listing photography / marketing prep | E159: Renovation | F159: project | G159: 250 | H159: 500 | I159: 1000 | J159: No | K159: Low | L159: 2026 St. Louis whole-house renovation guide + rehab planning allowance; verify with local bid | M159: https://www.angi.com/articles/complete-house-renovation-cost/mo/st-louis | N159: 0 | O159: 0 | P159: 1 | Q159: Professional/permit/waste cost classified as Other

Sheet Bid Comparison
A1: Cost Code / Scope | B1: Scope Description | C1: Vendor | D1: Bid Status | E1: Quoted Total | F1: Start Lead (days) | G1: Duration (days) | H1: Warranty | I1: Licensed/Insured? | J1: Permit Included? | K1: Payment Terms | L1: Notes
D2: Requested | E2: 0 | F2: 0 | G2: 0 | I2: Unknown | J2: Unknown
D3: Requested | E3: 0 | F3: 0 | G3: 0 | I3: Unknown | J3: Unknown
D4: Requested | E4: 0 | F4: 0 | G4: 0 | I4: Unknown | J4: Unknown
D5: Requested | E5: 0 | F5: 0 | G5: 0 | I5: Unknown | J5: Unknown
D6: Requested | E6: 0 | F6: 0 | G6: 0 | I6: Unknown | J6: Unknown
D7: Requested | E7: 0 | F7: 0 | G7: 0 | I7: Unknown | J7: Unknown
D8: Requested | E8: 0 | F8: 0 | G8: 0 | I8: Unknown | J8: Unknown
D9: Requested | E9: 0 | F9: 0 | G9: 0 | I9: Unknown | J9: Unknown
D10: Requested | E10: 0 | F10: 0 | G10: 0 | I10: Unknown | J10: Unknown
D11: Requested | E11: 0 | F11: 0 | G11: 0 | I11: Unknown | J11: Unknown
D12: Requested | E12: 0 | F12: 0 | G12: 0 | I12: Unknown | J12: Unknown
D13: Requested | E13: 0 | F13: 0 | G13: 0 | I13: Unknown | J13: Unknown
... D101: Requested | E101: 0 | F101: 0 | G101: 0 | I101: Unknown | J101: Unknown

Sheet Flip Analysis
A1: FLIP ECONOMICS & MAXIMUM ALLOWABLE OFFER
A3: Metric | B3: Formula / Source | C3: Amount
A4: Purchase Price | B4: Project Inputs | C4: ='Project Inputs'!C8 -> 112000
A5: ARV | B5: Project Inputs | C5: ='Project Inputs'!C9 -> 285000
A6: Selected Rehab Budget | B6: Scope Builder - Included Items | C6: =SUM('Scope Builder'!U2:U251) -> 96690
A7: Buying Closing Costs | B7: Purchase Price × input % | C7: =C4*'Project Inputs'!C10 -> 2240
A8: Selling Costs | B8: ARV × input % | C8: =C5*'Project Inputs'!C11 -> 22800
A9: Holding Costs | B9: Months × monthly holding | C9: ='Project Inputs'!C12*'Project Inputs'!C13 -> 8500
A10: Financing / Points | B10: Project Inputs | C10: ='Project Inputs'!C14 -> 4500
A11: Total Project Cost | B11: Purchase + rehab + transaction + holding | C11: =SUM(C4,C6:C10) -> 246730
A12: Projected Profit | B12: ARV − total project cost | C12: =C5-C11 -> 38270
A13: Profit Margin | B13: Profit ÷ ARV | C13: =IF(C5=0,0,C12/C5) -> 0.1342807
A14: Cash-on-Cost ROI | B14: Profit ÷ total project cost | C14: =IF(C11=0,0,C12/C11) -> 0.15510882
A15: 70% Rule MAO | B15: ARV × rule − rehab | C15: =C5*'Project Inputs'!C17-C6 -> 102810
A16: Detailed MAO | B16: Solve for purchase price using target profit | C16: =(C5-(C5*'Project Inputs'!C11)-C6-C9-C10-'Project Inputs'!C16)/(1+'Project Inputs'!C10) -> 115205.88
A17: MAO Buffer | B17: Detailed MAO − Purchase Price | C17: =C16-C4 -> 3205.8824
A20: PERFORMANCE KPIs
A21: Metric | B21: Formula / Source | C21: Amount
A22: Planned Rehab Days | B22: Project Inputs | C22: =IF('Project Inputs'!G4="","",'Project Inputs'!G4) -> 60
A23: Actual Rehab Days | B23: Project Inputs | C23: =IF('Project Inputs'!G5="","",'Project Inputs'!G5) -> 72
A24: Schedule Variance | B24: Actual Rehab Days − Planned Rehab Days | C24: =IF(OR(C22="",C23=""),"",C23-C22) -> 12
A25: Total Project Days | B25: Project Inputs | C25: =IF('Project Inputs'!G6="","",'Project Inputs'!G6) -> 128
A26: Holding Cost / Day | B26: Monthly Holding Cost ÷ 30.44 | C26: =IF('Project Inputs'!C13=0,0,'Project Inputs'!C13/30.44) -> 55.847569
A27: Rehab $ / sf | B27: Selected Rehab Budget ÷ Living Area | C27: =IF('Project Inputs'!C6=0,0,C6/'Project Inputs'!C6) -> 64.46
A28: Planned Contingency Reserve | B28: Budget incl. contingency − base rehab | C28: =SUM('Scope Builder'!U2:U251)-SUM('Scope Builder'!S2:S251) -> 8790
A29: Contingency Used | B29: MAX(0, Actual Rehab − base rehab) | C29: =IF(C31="","",MAX(0,C31-SUM('Scope Builder'!S2:S251))) -> 11900
A30: Contingency Remaining | B30: Reserve − contingency used, floored at zero | C30: =IF(C29="","",MAX(0,C28-C29)) -> 0
A31: Actual Rehab Cost | B31: Project Inputs | C31: =IF('Project Inputs'!G7="","",'Project Inputs'!G7) -> 99800
A32: Actual Sale Price | B32: Project Inputs | C32: =IF('Project Inputs'!G8="","",'Project Inputs'!G8) -> 292000
A33: ARV Variance | B33: Actual Sale Price − ARV | C33: =IF(C32="","",C32-C5) -> 7000
A34: Actual-vs-Budget Variance $ | B34: Actual Rehab − Budgeted Rehab | C34: =IF(C31="","",C31-C6) -> 3110
A35: Actual-vs-Budget Variance % | B35: Variance ÷ Budgeted Rehab | C35: =IF(OR(C6=0,C34=""),0,C34/C6) -> 0.03216465
A36: Actual Holding Cost | B36: Holding Cost / Day × Total Project Days | C36: =IF(C25="","",C26*C25) -> 7148.4888
A37: Actual Selling Costs | B37: Actual Sale Price × Selling Cost % | C37: =IF(C32="","",C32*'Project Inputs'!C11) -> 23360
A38: Actual Total Project Cost | B38: Purchase + rehab + transaction + holding | C38: =IF(OR(C31="",C32="",C25=""),"",C4+C31+C7+C37+C36+C10) -> 249048.49
A39: Actual Net Profit | B39: Actual Sale Price − Actual Total Project Cost | C39: =IF(OR(C32="",C38=""),"",C32-C38) -> 42951.511
A40: Profit / Day | B40: Actual Net Profit ÷ Total Project Days | C40: =IF(OR(C39="",C25=0),"",C39/C25) -> 335.55868

Sheet Sources & Notes
A1: SOURCE NOTES & COST LIMITATIONS
A3: Important | B3: The cost library is an acquisition-planning tool, not a bid. Costs vary by exact scope, house age, access, code requirements, hidden damage, material grade, and contractor availability.
A4: Market | B4: Anchored to St. Louis / Missouri where 2026 local guides were available. Other rows use rehab planning allowances and must be validated locally.
A5: Inspector | B5: Home inspectors identify conditions and safety concerns; they generally do not create a construction scope or guaranteed repair price. Specialty evaluation may be required.
A6: Appraiser | B6: Use the appraiser primarily to validate current/as-repaired value and market reaction; do not treat appraisal adjustments as a contractor quote.
A7: Interior Designer | B7: Use designer estimates for finish selections, material level, functionality, and value-add scope; validate installed cost with contractors.
A8: Flipper Discipline | B8: Before a non-trivial acquisition, obtain specialty bids for structure, sewer, roof, HVAC, major electrical, plumbing, water intrusion, mold/asbestos/lead where applicable.
A10: Source | B10: Key 2026 Data Point | C10: URL | D10: Accessed
A11: Angi — St. Louis roof replacement | B11: Average $8,155; typical $5,433–$11,032 | C11: https://www.angi.com/articles/how-much-does-roof-replacement-cost/mo/st-louis | D11: 2026-08-14
A12: Angi — St. Louis HVAC replacement | B12: Average $7,133; typical $4,755–$11,888 | C12: https://www.angi.com/articles/insider-s-price-guide-new-heating-and-cooling-system/mo/st-louis | D12: 2026-08-14
A13: Angi — St. Louis bathroom remodel | B13: Average $11,246; typical $6,423–$16,519 | C13: https://www.angi.com/articles/how-much-does-bathroom-remodel-cost/mo/st-louis | D13: 2026-08-14
A14: Angi — St. Louis whole-house renovation | B14: Kitchen $13,800–$38,600; bathroom $6,190–$26,700 | C14: https://www.angi.com/articles/complete-house-renovation-cost/mo/st-louis | D14: 2026-08-14
A15: Angi — St. Louis flooring | B15: Installed flooring roughly $2–$20/sf depending on material | C15: https://www.angi.com/articles/how-much-should-my-new-floor-cost/mo/st-louis | D15: 2026-08-14
A16: Angi — St. Louis window replacement | B16: Average $6,278; many projects $3,108–$9,479 | C16: https://www.angi.com/articles/how-much-does-window-replacement-cost/mo/st-louis | D16: 2026-08-14
A17: Angi — Foundation repair | B17: Average range roughly $2,225–$8,133 depending on damage | C17: https://www.angi.com/articles/how-much-does-foundation-repair-cost.htm | D17: 2026-08-14
A18: Angi — St. Louis main water line | B18: Average $2,231; typical $1,214–$3,247; $50–$150/lf | C18: https://www.angi.com/articles/what-general-cost-water-main-line-replacement/mo/st-louis | D18: 2026-08-14
A19: Angi — Water heater replacement | B19: Tank style roughly $881–$1,826; tankless $1,400–$3,900 | C19: https://www.angi.com/articles/how-much-does-water-heater-installation-cost.htm | D19: 2026-08-14
A20: Angi — St. Louis water damage restoration | B20: Roughly $3–$7.50/sf | C20: https://www.angi.com/articles/how-much-does-it-cost-repair-water-damage/mo/st-louis | D20: 2026-08-14
A21: Angi — St. Louis cabinet painting | B21: Roughly $30–$60 per linear foot | C21: https://www.angi.com/articles/how-much-does-it-cost-paint-kitchen-cabinets/mo/st-louis | D21: 2026-08-14

Sheet Lists
A1: Cost Codes | B1: Include | C1: Source | D1: Severity | E1: Priority | F1: Cost Basis | G1: Status | H1: YesNoUnknown | I1: Categories | J1: Bid Status
A2: STR-001 | B2: Yes | C2: Home Inspector | D2: Critical | E2: P0 - Immediate/Safety | F2: Low | G2: Not Started | H2: Yes | I2: Appliances & Curb Appeal | J2: Requested
A3: STR-002 | B3: No | C3: Appraiser | D3: High | E3: P1 - Before Offer | F3: Typical | G3: Bid Requested | H3: No | I3: Basement & Environmental | J3: Received
A4: STR-003 | C4: Interior Designer | D4: Medium | E4: P2 - Before Sale | F4: High | G4: Quoted | H4: Unknown | I4: Bathrooms | J4: Selected
A5: STR-004 | C5: Contractor | D5: Low | E5: P3 - Value Add | F5: Contractor Quote | G5: Approved | I5: Electrical | J5: Rejected
A6: STR-005 | C6: Owner/Flipper | E6: P4 - Optional | F6: Detailed Breakdown | G6: In Progress | I6: Exterior & Site
A7: STR-006 | C7: Municipality | G7: Complete | I7: Flooring
A8: STR-007 | C8: Specialist | G8: Deferred | I8: HVAC
A9: STR-008 | I9: Interior Finishes
A10: STR-009 | I10: Kitchen
A11: STR-010 | I11: Plumbing & Sewer
A12: STR-011 | I12: Roof & Attic
A13: ROF-001 | I13: Soft Costs & Due Diligence
A14: ROF-002 | I14: Structure & Foundation
A15: ROF-003 | I15: Windows, Doors & Garage
A16: ROF-004
A17: ROF-005
A18: ROF-006
A19: ROF-007
A20: ROF-008
A21: ROF-009
A22: ROF-010
A23: ROF-011
A24: EXT-001
A25: EXT-002
A26: EXT-003
A27: EXT-004
... A159: SOFT-010

Sheet Cost Dashboard
A1: REHAB COST BREAKDOWN DASHBOARD
A2: Material/labor/other allocations are planning estimates unless Cost Basis = Detailed Breakdown. Contractor quotes should be split when the vendor provides detail.
A4: ="Material Cost"&CHAR(10)&TEXT(SUM('Scope Builder'!AM2:AM251),"$#,##0") -> Material Cost $42,769 | D4: ="Labor Cost"&CHAR(10)&TEXT(SUM('Scope Builder'!AN2:AN251),"$#,##0") -> Labor Cost $32,830 | G4: ="Other Cost"&CHAR(10)&TEXT(SUM('Scope Builder'!AO2:AO251),"$#,##0") -> Other Cost $12,301 | J4: ="Contingency"&CHAR(10)&TEXT(SUM('Scope Builder'!AP2:AP251),"$#,##0") -> Contingency $8,790
A8: ="Material %"&CHAR(10)&TEXT(IF(SUM('Scope Builder'!S2:S251)=0,0,SUM('Scope Builder'!AM2:AM251)/SUM('Scope Builder'!S2:S251)),"0.0%") -> Material % 48.7% | D8: ="Labor %"&CHAR(10)&TEXT(IF(SUM('Scope Builder'!S2:S251)=0,0,SUM('Scope Builder'!AN2:AN251)/SUM('Scope Builder'!S2:S251)),"0.0%") -> Labor % 37.3% | G8: ="Other %"&CHAR(10)&TEXT(IF(SUM('Scope Builder'!S2:S251)=0,0,SUM('Scope Builder'!AO2:AO251)/SUM('Scope Builder'!S2:S251)),"0.0%") -> Other % 14.0% | J8: ="Labor / Material"&CHAR(10)&TEXT(IF(SUM('Scope Builder'!AM2:AM251)=0,0,SUM('Scope Builder'!AN2:AN251)/SUM('Scope Builder'!AM2:AM251)),"0.00x") -> Labor / Material 0.77x
A12: COST QUALITY & COVERAGE
A13: Base Rehab Before Contingency | D13: =SUM('Scope Builder'!S2:S251) -> 87900
A14: Total Rehab incl. Contingency | D14: =SUM('Scope Builder'!U2:U251) -> 96690
A15: Detailed Breakdown Coverage | D15: =IF(SUM('Scope Builder'!U2:U251)=0,0,SUMIFS('Scope Builder'!U2:U251,'Scope Builder'!R2:R251,"Detailed Breakdown")/SUM('Scope Builder'!U2:U251)) -> 0.98350398
A16: Contractor Quote Coverage | D16: =IF(SUM('Scope Builder'!U2:U251)=0,0,SUMIFS('Scope Builder'!U2:U251,'Scope Builder'!R2:R251,"Contractor Quote")/SUM('Scope Builder'!U2:U251)) -> 0.016496018
A17: Planning Allowance Coverage | D17: =IF(SUM('Scope Builder'!U2:U251)=0,0,SUMIFS('Scope Builder'!U2:U251,'Scope Builder'!R2:R251,"Low")/SUM('Scope Builder'!U2:U251)+SUMIFS('Scope Builder'!U2:U251,'Scope Builder'!R2:R251,"Typical")/SUM('Scope Builder'!U2:U251)+SUMIFS('Scope Builder'!U2:U251,'Scope Builder'!R2:R251,"High")/SUM('Scope Builder'!U2:U251)) -> 0
A20: COST COMPONENT SUMMARY | F20: MATERIAL / LABOR / OTHER BY CATEGORY
A21: Component | B21: Cost | C21: % of Base | D21: % of Total Rehab | F21: Category | G21: Material | H21: Labor | I21: Other | J21: Contingency | K21: Total Rehab
A22: Material | B22: =SUM('Scope Builder'!AM2:AM251) -> 42769 | C22: =IF(SUM('Scope Builder'!S2:S251)=0,0,B22/SUM('Scope Builder'!S2:S251)) -> 0.48656428 | D22: =IF(SUM('Scope Builder'!U2:U251)=0,0,B22/SUM('Scope Builder'!U2:U251)) -> 0.44233116 | F22: Appliances & Curb Appeal | G22: =SUMIFS('Scope Builder'!$AM$2:$AM$251,'Scope Builder'!$A$2:$A$251,"Yes",'Scope Builder'!$C$2:$C$251,F22) -> 150 | H22: =SUMIFS('Scope Builder'!$AN$2:$AN$251,'Scope Builder'!$A$2:$A$251,"Yes",'Scope Builder'!$C$2:$C$251,F22) -> 250 | I22: =SUMIFS('Scope Builder'!$AO$2:$AO$251,'Scope Builder'!$A$2:$A$251,"Yes",'Scope Builder'!$C$2:$C$251,F22) -> 50 | J22: =SUMIFS('Scope Builder'!$AP$2:$AP$251,'Scope Builder'!$A$2:$A$251,"Yes",'Scope Builder'!$C$2:$C$251,F22) -> 45 | K22: =SUMIFS('Scope Builder'!$U$2:$U$251,'Scope Builder'!$A$2:$A$251,"Yes",'Scope Builder'!$C$2:$C$251,F22) -> 495
A23: Labor | B23: =SUM('Scope Builder'!AN2:AN251) -> 32830 | C23: =IF(SUM('Scope Builder'!S2:S251)=0,0,B23/SUM('Scope Builder'!S2:S251)) -> 0.37349261 | D23: =IF(SUM('Scope Builder'!U2:U251)=0,0,B23/SUM('Scope Builder'!U2:U251)) -> 0.33953873 | F23: Basement & Environmental | G23: =SUMIFS('Scope Builder'!$AM$2:$AM$251,'Scope Builder'!$A$2:$A$251,"Yes",'Scope Builder'!$C$2:$C$251,F23) -> 0 | H23: =SUMIFS('Scope Builder'!$AN$2:$AN$251,'Scope Builder'!$A$2:$A$251,"Yes",'Scope Builder'!$C$2:$C$251,F23) -> 0 | I23: =SUMIFS('Scope Builder'!$AO$2:$AO$251,'Scope Builder'!$A$2:$A$251,"Yes",'Scope Builder'!$C$2:$C$251,F23) -> 0 | J23: =SUMIFS('Scope Builder'!$AP$2:$AP$251,'Scope Builder'!$A$2:$A$251,"Yes",'Scope Builder'!$C$2:$C$251,F23) -> 0 | K23: =SUMIFS('Scope Builder'!$U$2:$U$251,'Scope Builder'!$A$2:$A$251,"Yes",'Scope Builder'!$C$2:$C$251,F23) -> 0
A24: Other | B24: =SUM('Scope Builder'!AO2:AO251) -> 12301 | C24: =IF(SUM('Scope Builder'!S2:S251)=0,0,B24/SUM('Scope Builder'!S2:S251)) -> 0.13994312 | D24: =IF(SUM('Scope Builder'!U2:U251)=0,0,B24/SUM('Scope Builder'!U2:U251)) -> 0.12722102 | F24: Bathrooms | G24: =SUMIFS('Scope Builder'!$AM$2:$AM$251,'Scope Builder'!$A$2:$A$251,"Yes",'Scope Builder'!$C$2:$C$251,F24) -> 6800 | H24: =SUMIFS('Scope Builder'!$AN$2:$AN$251,'Scope Builder'!$A$2:$A$251,"Yes",'Scope Builder'!$C$2:$C$251,F24) -> 4600 | I24: =SUMIFS('Scope Builder'!$AO$2:$AO$251,'Scope Builder'!$A$2:$A$251,"Yes",'Scope Builder'!$C$2:$C$251,F24) -> 1300 | J24: =SUMIFS('Scope Builder'!$AP$2:$AP$251,'Scope Builder'!$A$2:$A$251,"Yes",'Scope Builder'!$C$2:$C$251,F24) -> 1270 | K24: =SUMIFS('Scope Builder'!$U$2:$U$251,'Scope Builder'!$A$2:$A$251,"Yes",'Scope Builder'!$C$2:$C$251,F24) -> 13970
A25: Contingency | B25: =SUM('Scope Builder'!AP2:AP251) -> 8790 | C25: =0 -> 0 | D25: =IF(SUM('Scope Builder'!U2:U251)=0,0,B25/SUM('Scope Builder'!U2:U251)) -> 0.090909091 | F25: Electrical | G25: =SUMIFS('Scope Builder'!$AM$2:$AM$251,'Scope Builder'!$A$2:$A$251,"Yes",'Scope Builder'!$C$2:$C$251,F25) -> 1450 | H25: =SUMIFS('Scope Builder'!$AN$2:$AN$251,'Scope Builder'!$A$2:$A$251,"Yes",'Scope Builder'!$C$2:$C$251,F25) -> 1800 | I25: =SUMIFS('Scope Builder'!$AO$2:$AO$251,'Scope Builder'!$A$2:$A$251,"Yes",'Scope Builder'!$C$2:$C$251,F25) -> 350 | J25: =SUMIFS('Scope Builder'!$AP$2:$AP$251,'Scope Builder'!$A$2:$A$251,"Yes",'Scope Builder'!$C$2:$C$251,F25) -> 360 | K25: =SUMIFS('Scope Builder'!$U$2:$U$251,'Scope Builder'!$A$2:$A$251,"Yes",'Scope Builder'!$C$2:$C$251,F25) -> 3960
F26: Exterior & Site | G26: =SUMIFS('Scope Builder'!$AM$2:$AM$251,'Scope Builder'!$A$2:$A$251,"Yes",'Scope Builder'!$C$2:$C$251,F26) -> 1000 | H26: =SUMIFS('Scope Builder'!$AN$2:$AN$251,'Scope Builder'!$A$2:$A$251,"Yes",'Scope Builder'!$C$2:$C$251,F26) -> 1000 | I26: =SUMIFS('Scope Builder'!$AO$2:$AO$251,'Scope Builder'!$A$2:$A$251,"Yes",'Scope Builder'!$C$2:$C$251,F26) -> 300 | J26: =SUMIFS('Scope Builder'!$AP$2:$AP$251,'Scope Builder'!$A$2:$A$251,"Yes",'Scope Builder'!$C$2:$C$251,F26) -> 230 | K26: =SUMIFS('Scope Builder'!$U$2:$U$251,'Scope Builder'!$A$2:$A$251,"Yes",'Scope Builder'!$C$2:$C$251,F26) -> 2530
F27: Flooring | G27: =SUMIFS('Scope Builder'!$AM$2:$AM$251,'Scope Builder'!$A$2:$A$251,"Yes",'Scope Builder'!$C$2:$C$251,F27) -> 3894 | H27: =SUMIFS('Scope Builder'!$AN$2:$AN$251,'Scope Builder'!$A$2:$A$251,"Yes",'Scope Builder'!$C$2:$C$251,F27) -> 2880 | I27: =SUMIFS('Scope Builder'!$AO$2:$AO$251,'Scope Builder'!$A$2:$A$251,"Yes",'Scope Builder'!$C$2:$C$251,F27) -> 826 | J27: =SUMIFS('Scope Builder'!$AP$2:$AP$251,'Scope Builder'!$A$2:$A$251,"Yes",'Scope Builder'!$C$2:$C$251,F27) -> 760 | K27: =SUMIFS('Scope Builder'!$U$2:$U$251,'Scope Builder'!$A$2:$A$251,"Yes",'Scope Builder'!$C$2:$C$251,F27) -> 8360
F28: HVAC | G28: =SUMIFS('Scope Builder'!$AM$2:$AM$251,'Scope Builder'!$A$2:$A$251,"Yes",'Scope Builder'!$C$2:$C$251,F28) -> 4600 | H28: =SUMIFS('Scope Builder'!$AN$2:$AN$251,'Scope Builder'!$A$2:$A$251,"Yes",'Scope Builder'!$C$2:$C$251,F28) -> 2800 | I28: =SUMIFS('Scope Builder'!$AO$2:$AO$251,'Scope Builder'!$A$2:$A$251,"Yes",'Scope Builder'!$C$2:$C$251,F28) -> 500 | J28: =SUMIFS('Scope Builder'!$AP$2:$AP$251,'Scope Builder'!$A$2:$A$251,"Yes",'Scope Builder'!$C$2:$C$251,F28) -> 790 | K28: =SUMIFS('Scope Builder'!$U$2:$U$251,'Scope Builder'!$A$2:$A$251,"Yes",'Scope Builder'!$C$2:$C$251,F28) -> 8690
F29: Interior Finishes | G29: =SUMIFS('Scope Builder'!$AM$2:$AM$251,'Scope Builder'!$A$2:$A$251,"Yes",'Scope Builder'!$C$2:$C$251,F29) -> 1575 | H29: =SUMIFS('Scope Builder'!$AN$2:$AN$251,'Scope Builder'!$A$2:$A$251,"Yes",'Scope Builder'!$C$2:$C$251,F29) -> 2700 | I29: =SUMIFS('Scope Builder'!$AO$2:$AO$251,'Scope Builder'!$A$2:$A$251,"Yes",'Scope Builder'!$C$2:$C$251,F29) -> 325 | J29: =SUMIFS('Scope Builder'!$AP$2:$AP$251,'Scope Builder'!$A$2:$A$251,"Yes",'Scope Builder'!$C$2:$C$251,F29) -> 460 | K29: =SUMIFS('Scope Builder'!$U$2:$U$251,'Scope Builder'!$A$2:$A$251,"Yes",'Scope Builder'!$C$2:$C$251,F29) -> 5060
F30: Kitchen | G30: =SUMIFS('Scope Builder'!$AM$2:$AM$251,'Scope Builder'!$A$2:$A$251,"Yes",'Scope Builder'!$C$2:$C$251,F30) -> 14000 | H30: =SUMIFS('Scope Builder'!$AN$2:$AN$251,'Scope Builder'!$A$2:$A$251,"Yes",'Scope Builder'!$C$2:$C$251,F30) -> 8000 | I30: =SUMIFS('Scope Builder'!$AO$2:$AO$251,'Scope Builder'!$A$2:$A$251,"Yes",'Scope Builder'!$C$2:$C$251,F30) -> 2500 | J30: =SUMIFS('Scope Builder'!$AP$2:$AP$251,'Scope Builder'!$A$2:$A$251,"Yes",'Scope Builder'!$C$2:$C$251,F30) -> 2450 | K30: =SUMIFS('Scope Builder'!$U$2:$U$251,'Scope Builder'!$A$2:$A$251,"Yes",'Scope Builder'!$C$2:$C$251,F30) -> 26950
F31: Plumbing & Sewer | G31: =SUMIFS('Scope Builder'!$AM$2:$AM$251,'Scope Builder'!$A$2:$A$251,"Yes",'Scope Builder'!$C$2:$C$251,F31) -> 1800 | H31: =SUMIFS('Scope Builder'!$AN$2:$AN$251,'Scope Builder'!$A$2:$A$251,"Yes",'Scope Builder'!$C$2:$C$251,F31) -> 3000 | I31: =SUMIFS('Scope Builder'!$AO$2:$AO$251,'Scope Builder'!$A$2:$A$251,"Yes",'Scope Builder'!$C$2:$C$251,F31) -> 2700 | J31: =SUMIFS('Scope Builder'!$AP$2:$AP$251,'Scope Builder'!$A$2:$A$251,"Yes",'Scope Builder'!$C$2:$C$251,F31) -> 750 | K31: =SUMIFS('Scope Builder'!$U$2:$U$251,'Scope Builder'!$A$2:$A$251,"Yes",'Scope Builder'!$C$2:$C$251,F31) -> 8250
F32: Roof & Attic | G32: =SUMIFS('Scope Builder'!$AM$2:$AM$251,'Scope Builder'!$A$2:$A$251,"Yes",'Scope Builder'!$C$2:$C$251,F32) -> 4200 | H32: =SUMIFS('Scope Builder'!$AN$2:$AN$251,'Scope Builder'!$A$2:$A$251,"Yes",'Scope Builder'!$C$2:$C$251,F32) -> 4000 | I32: =SUMIFS('Scope Builder'!$AO$2:$AO$251,'Scope Builder'!$A$2:$A$251,"Yes",'Scope Builder'!$C$2:$C$251,F32) -> 1700 | J32: =SUMIFS('Scope Builder'!$AP$2:$AP$251,'Scope Builder'!$A$2:$A$251,"Yes",'Scope Builder'!$C$2:$C$251,F32) -> 990 | K32: =SUMIFS('Scope Builder'!$U$2:$U$251,'Scope Builder'!$A$2:$A$251,"Yes",'Scope Builder'!$C$2:$C$251,F32) -> 10890
F33: Soft Costs & Due Diligence | G33: =SUMIFS('Scope Builder'!$AM$2:$AM$251,'Scope Builder'!$A$2:$A$251,"Yes",'Scope Builder'!$C$2:$C$251,F33) -> 0 | H33: =SUMIFS('Scope Builder'!$AN$2:$AN$251,'Scope Builder'!$A$2:$A$251,"Yes",'Scope Builder'!$C$2:$C$251,F33) -> 0 | I33: =SUMIFS('Scope Builder'!$AO$2:$AO$251,'Scope Builder'!$A$2:$A$251,"Yes",'Scope Builder'!$C$2:$C$251,F33) -> 800 | J33: =SUMIFS('Scope Builder'!$AP$2:$AP$251,'Scope Builder'!$A$2:$A$251,"Yes",'Scope Builder'!$C$2:$C$251,F33) -> 80 | K33: =SUMIFS('Scope Builder'!$U$2:$U$251,'Scope Builder'!$A$2:$A$251,"Yes",'Scope Builder'!$C$2:$C$251,F33) -> 880
F34: Structure & Foundation | G34: =SUMIFS('Scope Builder'!$AM$2:$AM$251,'Scope Builder'!$A$2:$A$251,"Yes",'Scope Builder'!$C$2:$C$251,F34) -> 0 | H34: =SUMIFS('Scope Builder'!$AN$2:$AN$251,'Scope Builder'!$A$2:$A$251,"Yes",'Scope Builder'!$C$2:$C$251,F34) -> 0 | I34: =SUMIFS('Scope Builder'!$AO$2:$AO$251,'Scope Builder'!$A$2:$A$251,"Yes",'Scope Builder'!$C$2:$C$251,F34) -> 650 | J34: =SUMIFS('Scope Builder'!$AP$2:$AP$251,'Scope Builder'!$A$2:$A$251,"Yes",'Scope Builder'!$C$2:$C$251,F34) -> 65 | K34: =SUMIFS('Scope Builder'!$U$2:$U$251,'Scope Builder'!$A$2:$A$251,"Yes",'Scope Builder'!$C$2:$C$251,F34) -> 715
F35: Windows, Doors & Garage | G35: =SUMIFS('Scope Builder'!$AM$2:$AM$251,'Scope Builder'!$A$2:$A$251,"Yes",'Scope Builder'!$C$2:$C$251,F35) -> 3300 | H35: =SUMIFS('Scope Builder'!$AN$2:$AN$251,'Scope Builder'!$A$2:$A$251,"Yes",'Scope Builder'!$C$2:$C$251,F35) -> 1800 | I35: =SUMIFS('Scope Builder'!$AO$2:$AO$251,'Scope Builder'!$A$2:$A$251,"Yes",'Scope Builder'!$C$2:$C$251,F35) -> 300 | J35: =SUMIFS('Scope Builder'!$AP$2:$AP$251,'Scope Builder'!$A$2:$A$251,"Yes",'Scope Builder'!$C$2:$C$251,F35) -> 540 | K35: =SUMIFS('Scope Builder'!$U$2:$U$251,'Scope Builder'!$A$2:$A$251,"Yes",'Scope Builder'!$C$2:$C$251,F35) -> 5940
A52: BALLPARK vs DETAILED COST
A53: Comparable variance uses only included items with a detailed takeoff. Ballpark cost and detailed cost both include contingency; Estimate Maturity is dollar-weighted detailed coverage.
A55: ="Ballpark Total"&CHAR(10)&TEXT(SUM('Scope Builder'!AW2:AW251),"$#,##0") -> Ballpark Total $88,807 | D55: ="Detailed Cost"&CHAR(10)&TEXT(SUM('Scope Builder'!AX2:AX251),"$#,##0") -> Detailed Cost $95,095 | G55: ="Variance on Detailed Items"&CHAR(10)&TEXT(SUM('Scope Builder'!AZ2:AZ251),"$#,##0") -> Variance on Detailed Items $8,048 | J55: ="Estimate Maturity"&CHAR(10)&TEXT(IF(SUM('Scope Builder'!AW2:AW251)=0,0,SUM('Scope Builder'!AY2:AY251)/SUM('Scope Builder'!AW2:AW251)),"0.0%") -> Estimate Maturity 98.0%
A60: Category | B60: Comparable Ballpark | C60: Detailed Cost | D60: Variance | H60: Estimate | I60: Cost
A61: Appliances & Curb Appeal | B61: =SUMIFS('Scope Builder'!$AY$2:$AY$251,'Scope Builder'!$C$2:$C$251,$A61) -> 440 | C61: =SUMIFS('Scope Builder'!$AX$2:$AX$251,'Scope Builder'!$C$2:$C$251,$A61) -> 495 | D61: =$C61-$B61 -> 55 | H61: Comparable Ballpark | I61: =SUM('Scope Builder'!AY2:AY251) -> 87047.4
A62: Basement & Environmental | B62: =SUMIFS('Scope Builder'!$AY$2:$AY$251,'Scope Builder'!$C$2:$C$251,$A62) -> 0 | C62: =SUMIFS('Scope Builder'!$AX$2:$AX$251,'Scope Builder'!$C$2:$C$251,$A62) -> 0 | D62: =$C62-$B62 -> 0 | H62: Detailed Cost | I62: =SUM('Scope Builder'!AX2:AX251) -> 95095
A63: Bathrooms | B63: =SUMIFS('Scope Builder'!$AY$2:$AY$251,'Scope Builder'!$C$2:$C$251,$A63) -> 12370.6 | C63: =SUMIFS('Scope Builder'!$AX$2:$AX$251,'Scope Builder'!$C$2:$C$251,$A63) -> 13970 | D63: =$C63-$B63 -> 1599.4
A64: Electrical | B64: =SUMIFS('Scope Builder'!$AY$2:$AY$251,'Scope Builder'!$C$2:$C$251,$A64) -> 3300 | C64: =SUMIFS('Scope Builder'!$AX$2:$AX$251,'Scope Builder'!$C$2:$C$251,$A64) -> 3960 | D64: =$C64-$B64 -> 660
A65: Exterior & Site | B65: =SUMIFS('Scope Builder'!$AY$2:$AY$251,'Scope Builder'!$C$2:$C$251,$A65) -> 2200 | C65: =SUMIFS('Scope Builder'!$AX$2:$AX$251,'Scope Builder'!$C$2:$C$251,$A65) -> 2530 | D65: =$C65-$B65 -> 330
A66: Flooring | B66: =SUMIFS('Scope Builder'!$AY$2:$AY$251,'Scope Builder'!$C$2:$C$251,$A66) -> 7920 | C66: =SUMIFS('Scope Builder'!$AX$2:$AX$251,'Scope Builder'!$C$2:$C$251,$A66) -> 8360 | D66: =$C66-$B66 -> 440
A67: HVAC | B67: =SUMIFS('Scope Builder'!$AY$2:$AY$251,'Scope Builder'!$C$2:$C$251,$A67) -> 7846.3 | C67: =SUMIFS('Scope Builder'!$AX$2:$AX$251,'Scope Builder'!$C$2:$C$251,$A67) -> 8690 | D67: =$C67-$B67 -> 843.7
A68: Interior Finishes | B68: =SUMIFS('Scope Builder'!$AY$2:$AY$251,'Scope Builder'!$C$2:$C$251,$A68) -> 4950 | C68: =SUMIFS('Scope Builder'!$AX$2:$AX$251,'Scope Builder'!$C$2:$C$251,$A68) -> 5060 | D68: =$C68-$B68 -> 110
A69: Kitchen | B69: =SUMIFS('Scope Builder'!$AY$2:$AY$251,'Scope Builder'!$C$2:$C$251,$A69) -> 28600 | C69: =SUMIFS('Scope Builder'!$AX$2:$AX$251,'Scope Builder'!$C$2:$C$251,$A69) -> 26950 | D69: =$C69-$B69 -> -1650
A70: Plumbing & Sewer | B70: =SUMIFS('Scope Builder'!$AY$2:$AY$251,'Scope Builder'!$C$2:$C$251,$A70) -> 5500 | C70: =SUMIFS('Scope Builder'!$AX$2:$AX$251,'Scope Builder'!$C$2:$C$251,$A70) -> 8250 | D70: =$C70-$B70 -> 2750
A71: Roof & Attic | B71: =SUMIFS('Scope Builder'!$AY$2:$AY$251,'Scope Builder'!$C$2:$C$251,$A71) -> 8970.5 | C71: =SUMIFS('Scope Builder'!$AX$2:$AX$251,'Scope Builder'!$C$2:$C$251,$A71) -> 10890 | D71: =$C71-$B71 -> 1919.5
A72: Soft Costs & Due Diligence | B72: =SUMIFS('Scope Builder'!$AY$2:$AY$251,'Scope Builder'!$C$2:$C$251,$A72) -> 0 | C72: =SUMIFS('Scope Builder'!$AX$2:$AX$251,'Scope Builder'!$C$2:$C$251,$A72) -> 0 | D72: =$C72-$B72 -> 0
A73: Structure & Foundation | B73: =SUMIFS('Scope Builder'!$AY$2:$AY$251,'Scope Builder'!$C$2:$C$251,$A73) -> 0 | C73: =SUMIFS('Scope Builder'!$AX$2:$AX$251,'Scope Builder'!$C$2:$C$251,$A73) -> 0 | D73: =$C73-$B73 -> 0
A74: Windows, Doors & Garage | B74: =SUMIFS('Scope Builder'!$AY$2:$AY$251,'Scope Builder'!$C$2:$C$251,$A74) -> 4950 | C74: =SUMIFS('Scope Builder'!$AX$2:$AX$251,'Scope Builder'!$C$2:$C$251,$A74) -> 5940 | D74: =$C74-$B74 -> 990
A76: LABOR-TO-MATERIAL COST RATIO
A77: Comparison | B77: Ratio
A78: Material baseline | B78: 1
A79: Labor per $1 material | B79: =IFERROR(SUM('Scope Builder'!AN2:AN251)/SUM('Scope Builder'!AM2:AM251),0) -> 0.76761206
A81: ="Interpretation: $"&TEXT(B79,"0.00")&" of labor for every $1.00 of material." -> Interpretation: $0.77 of labor for every $1.00 of material.

Sheet Executive Overview
A1: HOUSE FLIP | EXECUTIVE OVERVIEW
P2: Priority | Q2: Budget | S2: Metric | T2: Amount
A3: Acquisition • Rehab • Risk • Profitability | Dynamic view of the current property model | P3: P0 - Immediate/Safety | Q3: =SUMIFS('Scope Builder'!$U$2:$U$251,'Scope Builder'!$A$2:$A$251,"Yes",'Scope Builder'!$K$2:$K$251,P3) -> 0 | S3: Purchase Price | T3: ='Flip Analysis'!C4 -> 112000
P4: P1 - Before Offer | Q4: =SUMIFS('Scope Builder'!$U$2:$U$251,'Scope Builder'!$A$2:$A$251,"Yes",'Scope Builder'!$K$2:$K$251,P4) -> 24695 | S4: Rehab Budget | T4: ='Flip Analysis'!C6 -> 96690
A5: ="Purchase Price"&CHAR(10)&TEXT('Flip Analysis'!C4,"$#,##0") -> Purchase Price $112,000 | D5: ="After Repair Value"&CHAR(10)&TEXT('Flip Analysis'!C5,"$#,##0") -> After Repair Value $285,000 | G5: ="Rehab Budget"&CHAR(10)&TEXT('Flip Analysis'!C6,"$#,##0") -> Rehab Budget $96,690 | J5: ="Projected Profit"&CHAR(10)&TEXT('Flip Analysis'!C12,"$#,##0") -> Projected Profit $38,270 | P5: P2 - Before Sale | Q5: =SUMIFS('Scope Builder'!$U$2:$U$251,'Scope Builder'!$A$2:$A$251,"Yes",'Scope Builder'!$K$2:$K$251,P5) -> 14630 | S5: Other Project Costs | T5: ='Flip Analysis'!C11-'Flip Analysis'!C4-'Flip Analysis'!C6 -> 38040
P6: P3 - Value Add | Q6: =SUMIFS('Scope Builder'!$U$2:$U$251,'Scope Builder'!$A$2:$A$251,"Yes",'Scope Builder'!$K$2:$K$251,P6) -> 57365 | S6: Projected Profit | T6: ='Flip Analysis'!C12 -> 38270
P7: P4 - Optional | Q7: =SUMIFS('Scope Builder'!$U$2:$U$251,'Scope Builder'!$A$2:$A$251,"Yes",'Scope Builder'!$K$2:$K$251,P7) -> 0
A10: ="Detailed MAO"&CHAR(10)&TEXT('Flip Analysis'!C16,"$#,##0") -> Detailed MAO $115,206 | D10: ="MAO Buffer"&CHAR(10)&TEXT('Flip Analysis'!C17,"$#,##0") -> MAO Buffer $3,206 | G10: ="Profit Margin"&CHAR(10)&TEXT('Flip Analysis'!C13,"0.0%") -> Profit Margin 13.4% | J10: ="Cash-on-Cost ROI"&CHAR(10)&TEXT('Flip Analysis'!C14,"0.0%") -> Cash-on-Cost ROI 15.5% | P10: Category | Q10: Budget
P11: Appliances & Curb Appeal | Q11: =SUMIFS('Scope Builder'!$U$2:$U$251,'Scope Builder'!$A$2:$A$251,"Yes",'Scope Builder'!$C$2:$C$251,P11) -> 495
P12: Basement & Environmental | Q12: =SUMIFS('Scope Builder'!$U$2:$U$251,'Scope Builder'!$A$2:$A$251,"Yes",'Scope Builder'!$C$2:$C$251,P12) -> 0
P13: Bathrooms | Q13: =SUMIFS('Scope Builder'!$U$2:$U$251,'Scope Builder'!$A$2:$A$251,"Yes",'Scope Builder'!$C$2:$C$251,P13) -> 13970
P14: Electrical | Q14: =SUMIFS('Scope Builder'!$U$2:$U$251,'Scope Builder'!$A$2:$A$251,"Yes",'Scope Builder'!$C$2:$C$251,P14) -> 3960
A15: ="DEAL HEALTH"&CHAR(10)&IF('Flip Analysis'!C17<0,"REVIEW — OVER MAO",IF('Flip Analysis'!C17/'Flip Analysis'!C4<0.05,"CAUTION — THIN BUFFER","WITHIN TARGET RANGE")) -> DEAL HEALTH CAUTION — THIN BUFFER | E15: ="Estimate Maturity"&CHAR(10)&TEXT(IF(SUM('Scope Builder'!AW2:AW251)=0,0,SUM('Scope Builder'!AY2:AY251)/SUM('Scope Builder'!AW2:AW251)),"0.0%") -> Estimate Maturity 98.0% | H15: ="Contractor Quote Coverage"&CHAR(10)&TEXT('Cost Dashboard'!D16,"0.0%") -> Contractor Quote Coverage 1.6% | K15: ="Critical Items"&CHAR(10)&TEXT(Dashboard!D10,"0") -> Critical Items 4 | P15: Exterior & Site | Q15: =SUMIFS('Scope Builder'!$U$2:$U$251,'Scope Builder'!$A$2:$A$251,"Yes",'Scope Builder'!$C$2:$C$251,P15) -> 2530
P16: Flooring | Q16: =SUMIFS('Scope Builder'!$U$2:$U$251,'Scope Builder'!$A$2:$A$251,"Yes",'Scope Builder'!$C$2:$C$251,P16) -> 8360
P17: HVAC | Q17: =SUMIFS('Scope Builder'!$U$2:$U$251,'Scope Builder'!$A$2:$A$251,"Yes",'Scope Builder'!$C$2:$C$251,P17) -> 8690
P18: Interior Finishes | Q18: =SUMIFS('Scope Builder'!$U$2:$U$251,'Scope Builder'!$A$2:$A$251,"Yes",'Scope Builder'!$C$2:$C$251,P18) -> 5060
P19: Kitchen | Q19: =SUMIFS('Scope Builder'!$U$2:$U$251,'Scope Builder'!$A$2:$A$251,"Yes",'Scope Builder'!$C$2:$C$251,P19) -> 26950
A20: BUDGET BY PRIORITY | G20: REHAB BUDGET BY CATEGORY | P20: Plumbing & Sewer | Q20: =SUMIFS('Scope Builder'!$U$2:$U$251,'Scope Builder'!$A$2:$A$251,"Yes",'Scope Builder'!$C$2:$C$251,P20) -> 8250
P21: Roof & Attic | Q21: =SUMIFS('Scope Builder'!$U$2:$U$251,'Scope Builder'!$A$2:$A$251,"Yes",'Scope Builder'!$C$2:$C$251,P21) -> 10890
P22: Soft Costs & Due Diligence | Q22: =SUMIFS('Scope Builder'!$U$2:$U$251,'Scope Builder'!$A$2:$A$251,"Yes",'Scope Builder'!$C$2:$C$251,P22) -> 880
P23: Structure & Foundation | Q23: =SUMIFS('Scope Builder'!$U$2:$U$251,'Scope Builder'!$A$2:$A$251,"Yes",'Scope Builder'!$C$2:$C$251,P23) -> 715
P24: Windows, Doors & Garage | Q24: =SUMIFS('Scope Builder'!$U$2:$U$251,'Scope Builder'!$A$2:$A$251,"Yes",'Scope Builder'!$C$2:$C$251,P24) -> 5940
A40: DEAL ECONOMICS | H40: MANAGEMENT SNAPSHOT
H41: Metric | J41: Value | L41: Interpretation
H42: Rehab $ / sf | J42: ='Flip Analysis'!C27 -> 64.46 | L42: Budgeted rehab intensity per living square foot
H43: Holding Cost / Day | J43: ='Flip Analysis'!C26 -> 55.847569 | L43: Daily carrying-cost penalty
H44: Profit / Day | J44: ='Flip Analysis'!C40 -> 335.55868 | L44: Capital productivity
H45: Schedule Variance | J45: ='Flip Analysis'!C24 -> 12 | L45: Positive = schedule slippage
H46: ARV Variance | J46: ='Flip Analysis'!C33 -> 7000 | L46: Positive = resale above ARV
H47: Actual vs Budget | J47: ='Flip Analysis'!C34 -> 3110 | L47: Positive = rehab overrun
A64: Decision-support dashboard. Replace worked-example inputs with property-specific inspections, takeoffs, contractor bids, financing assumptions, and actual sale data before making an investment decision.

Sheet Cost Analytics
A1: HOUSE FLIP | COST & VARIANCE ANALYTICS
P2: Component | Q2: Cost
A3: Ballpark vs detailed estimate • Cost structure • Variance • Estimate quality | P3: Material | Q3: ='Cost Dashboard'!B22 -> 42769
P4: Labor | Q4: ='Cost Dashboard'!B23 -> 32830
A5: ="Material Cost"&CHAR(10)&TEXT('Cost Dashboard'!B22,"$#,##0") -> Material Cost $42,769 | D5: ="Labor Cost"&CHAR(10)&TEXT('Cost Dashboard'!B23,"$#,##0") -> Labor Cost $32,830 | G5: ="Other Cost"&CHAR(10)&TEXT('Cost Dashboard'!B24,"$#,##0") -> Other Cost $12,301 | J5: ="Contingency"&CHAR(10)&TEXT('Cost Dashboard'!B25,"$#,##0") -> Contingency $8,790 | P5: Other | Q5: ='Cost Dashboard'!B24 -> 12301
P6: Contingency | Q6: ='Cost Dashboard'!B25 -> 8790
A10: ="Material %"&CHAR(10)&TEXT('Cost Dashboard'!C22,"0.0%") -> Material % 48.7% | D10: ="Labor %"&CHAR(10)&TEXT('Cost Dashboard'!C23,"0.0%") -> Labor % 37.3% | G10: ="Labor / Material"&CHAR(10)&TEXT('Cost Dashboard'!B79,"0.00")&"x" -> Labor / Material 0.77x | J10: ="Estimate Maturity"&CHAR(10)&TEXT(IF(SUM('Scope Builder'!AW2:AW251)=0,0,SUM('Scope Builder'!AY2:AY251)/SUM('Scope Builder'!AW2:AW251)),"0.0%") -> Estimate Maturity 98.0% | P10: Category | Q10: Ballpark | R10: Detailed
P11: Appliances & Curb Appeal | Q11: ='Cost Dashboard'!B61 -> 440 | R11: ='Cost Dashboard'!C61 -> 495
P12: Basement & Environmental | Q12: ='Cost Dashboard'!B62 -> 0 | R12: ='Cost Dashboard'!C62 -> 0
P13: Bathrooms | Q13: ='Cost Dashboard'!B63 -> 12370.6 | R13: ='Cost Dashboard'!C63 -> 13970
P14: Electrical | Q14: ='Cost Dashboard'!B64 -> 3300 | R14: ='Cost Dashboard'!C64 -> 3960
A15: COST COMPOSITION | G15: BALLPARK vs DETAILED BY CATEGORY | P15: Exterior & Site | Q15: ='Cost Dashboard'!B65 -> 2200 | R15: ='Cost Dashboard'!C65 -> 2530
P16: Flooring | Q16: ='Cost Dashboard'!B66 -> 7920 | R16: ='Cost Dashboard'!C66 -> 8360
P17: HVAC | Q17: ='Cost Dashboard'!B67 -> 7846.3 | R17: ='Cost Dashboard'!C67 -> 8690
P18: Interior Finishes | Q18: ='Cost Dashboard'!B68 -> 4950 | R18: ='Cost Dashboard'!C68 -> 5060
P19: Kitchen | Q19: ='Cost Dashboard'!B69 -> 28600 | R19: ='Cost Dashboard'!C69 -> 26950
P20: Plumbing & Sewer | Q20: ='Cost Dashboard'!B70 -> 5500 | R20: ='Cost Dashboard'!C70 -> 8250
P21: Roof & Attic | Q21: ='Cost Dashboard'!B71 -> 8970.5 | R21: ='Cost Dashboard'!C71 -> 10890
P22: Soft Costs & Due Diligence | Q22: ='Cost Dashboard'!B72 -> 0 | R22: ='Cost Dashboard'!C72 -> 0
P23: Structure & Foundation | Q23: ='Cost Dashboard'!B73 -> 0 | R23: ='Cost Dashboard'!C73 -> 0
P24: Windows, Doors & Garage | Q24: ='Cost Dashboard'!B74 -> 4950 | R24: ='Cost Dashboard'!C74 -> 5940
P28: Comparison | Q28: Ratio
P29: Material Baseline | Q29: 1
P30: Labor per $1 Material | Q30: ='Cost Dashboard'!B79 -> 0.76761206
P33: Category | Q33: Variance
P34: Appliances & Curb Appeal | Q34: ='Cost Dashboard'!D61 -> 55
A35: VARIANCE BY CATEGORY | I35: LABOR-TO-MATERIAL RATIO | P35: Basement & Environmental | Q35: ='Cost Dashboard'!D62 -> 0
P36: Bathrooms | Q36: ='Cost Dashboard'!D63 -> 1599.4
P37: Electrical | Q37: ='Cost Dashboard'!D64 -> 660
P38: Exterior & Site | Q38: ='Cost Dashboard'!D65 -> 330
P39: Flooring | Q39: ='Cost Dashboard'!D66 -> 440
P40: HVAC | Q40: ='Cost Dashboard'!D67 -> 843.7
P41: Interior Finishes | Q41: ='Cost Dashboard'!D68 -> 110
P42: Kitchen | Q42: ='Cost Dashboard'!D69 -> -1650
P43: Plumbing & Sewer | Q43: ='Cost Dashboard'!D70 -> 2750
P44: Roof & Attic | Q44: ='Cost Dashboard'!D71 -> 1919.5
P45: Soft Costs & Due Diligence | Q45: ='Cost Dashboard'!D72 -> 0
P46: Structure & Foundation | Q46: ='Cost Dashboard'!D73 -> 0
P47: Windows, Doors & Garage | Q47: ='Cost Dashboard'!D74 -> 990
I49: ESTIMATE QUALITY
I50: Metric | K50: Value | M50: Meaning
I51: Detailed Breakdown Coverage | K51: ='Cost Dashboard'!D15 -> 0.98350398 | M51: Share backed by detailed takeoff
I52: Contractor Quote Coverage | K52: ='Cost Dashboard'!D16 -> 0.016496018 | M52: Share backed by vendor quote
I53: Planning Allowance Coverage | K53: ='Cost Dashboard'!D17 -> 0 | M53: Share still on planning allowance
I54: Comparable Ballpark | K54: ='Cost Dashboard'!I61 -> 87047.4 | M54: Baseline for comparable detailed items
I55: Comparable Detailed | K55: ='Cost Dashboard'!I62 -> 95095 | M55: Detailed value for the same items
I56: Variance % | K56: =IF(K54=0,0,(K55-K54)/K54) -> 0.09245078 | M56: Detailed vs comparable ballpark
A58: Positive variance means detailed cost is above ballpark; negative variance means detailed cost is lower. Large positive variances deserve scope review before acquisition.
A64: Decision-support dashboard. Replace worked-example inputs with property-specific inspections, takeoffs, contractor bids, financing assumptions, and actual sale data before making an investment decision.

Sheet Project Performance
A1: HOUSE FLIP | PROJECT PERFORMANCE
P2: Schedule | Q2: Days
A3: Schedule • Actual cost • Resale performance • Profit velocity | P3: Planned Rehab | Q3: ='Flip Analysis'!C22 -> 60
P4: Actual Rehab | Q4: ='Flip Analysis'!C23 -> 72
A5: ="Schedule Variance"&CHAR(10)&TEXT('Flip Analysis'!C24,"+0;-0;0")&" days" -> Schedule Variance +12 days | D5: ="Holding Cost / Day"&CHAR(10)&TEXT('Flip Analysis'!C26,"$#,##0.00") -> Holding Cost / Day $55.85 | G5: ="Profit / Day"&CHAR(10)&TEXT('Flip Analysis'!C40,"$#,##0;[Red]($#,##0)") -> Profit / Day $336 | J5: ="Contingency Remaining"&CHAR(10)&TEXT('Flip Analysis'!C30,"$#,##0;[Red]($#,##0)") -> Contingency Remaining $0
P7: Rehab Cost | Q7: Amount
P8: Budgeted Rehab | Q8: ='Flip Analysis'!C6 -> 96690
P9: Actual Rehab | Q9: ='Flip Analysis'!C31 -> 99800
A10: ="ARV Variance"&CHAR(10)&TEXT('Flip Analysis'!C33,"$#,##0;[Red]($#,##0)") -> ARV Variance $7,000 | D10: ="Actual vs Budget"&CHAR(10)&TEXT('Flip Analysis'!C34,"$#,##0;[Red]($#,##0)") -> Actual vs Budget $3,110 | G10: ="Actual Net Profit"&CHAR(10)&TEXT('Flip Analysis'!C39,"$#,##0;[Red]($#,##0)") -> Actual Net Profit $42,952 | J10: ="Actual Sale Price"&CHAR(10)&TEXT('Flip Analysis'!C32,"$#,##0;[Red]($#,##0)") -> Actual Sale Price $292,000
P12: Resale | Q12: Amount
P13: ARV | Q13: ='Flip Analysis'!C5 -> 285000
P14: Actual Sale Price | Q14: ='Flip Analysis'!C32 -> 292000
A15: SCHEDULE PERFORMANCE | H15: COST PERFORMANCE
P17: Profit | Q17: Amount
P18: Projected Profit | Q18: ='Flip Analysis'!C12 -> 38270
P19: Actual Net Profit | Q19: ='Flip Analysis'!C39 -> 42951.511
A34: RESALE PERFORMANCE | H34: PROFIT PERFORMANCE
A53: PROJECT PERFORMANCE SCORECARD
A54: Metric | C54: Plan / Benchmark | E54: Actual | G54: Variance | I54: Direction | K54: Management Meaning
A55: Rehab Days | C55: ='Flip Analysis'!C22 -> 60 | E55: ='Flip Analysis'!C23 -> 72 | G55: ='Flip Analysis'!C24 -> 12 | I55: Lower is better | K55: Schedule control and carrying-cost exposure
A56: Rehab Cost | C56: ='Flip Analysis'!C6 -> 96690 | E56: ='Flip Analysis'!C31 -> 99800 | G56: ='Flip Analysis'!C34 -> 3110 | I56: Lower is better | K56: Scope / procurement / contractor cost control
A57: Sale Price vs ARV | C57: ='Flip Analysis'!C5 -> 285000 | E57: ='Flip Analysis'!C32 -> 292000 | G57: ='Flip Analysis'!C33 -> 7000 | I57: Higher is better | K57: Accuracy of ARV and resale execution
A58: Net Profit | C58: ='Flip Analysis'!C12 -> 38270 | E58: ='Flip Analysis'!C39 -> 42951.511 | G58: ='Flip Analysis'!C39-'Flip Analysis'!C12 -> 4681.5112 | I58: Higher is better | K58: Overall economic performance of the flip
A59: Profit / Day | C59: — | E59: ='Flip Analysis'!C40 -> 335.55868 | G59: — | I59: Higher is better | K59: Capital productivity and cycle-time efficiency
A60: Contingency Remaining | C60: ='Flip Analysis'!C28 -> 8790 | E60: ='Flip Analysis'!C30 -> 0 | G60: ='Flip Analysis'!C30-'Flip Analysis'!C28 -> -8790 | I60: Higher is better | K60: Remaining protection against unknown conditions
A61: MAO Buffer | C61: $0 minimum | E61: ='Flip Analysis'!C17 -> 3205.8824 | G61: ='Flip Analysis'!C17 -> 3205.8824 | I61: Positive is better | K61: Purchase discipline relative to detailed MAO
A64: Decision-support dashboard. Replace worked-example inputs with property-specific inspections, takeoffs, contractor bids, financing assumptions, and actual sale data before making an investment decision.
